{
  "updated_at_utc": "2026-03-24T11:10:34Z",
  "rows": [
    {
      "pair": "AUDCAD",
      "error": false,
      "w1_state": 0,
      "d1_state": 0,
      "h1_state": -1,
      "d1_ribbon_state": 0,
      "chg_cc_d1": -0.4457837585078211,
      "aligned": false,
      "aligned_w1_d1": false,
      "double_aligned": false,
      "direction": "NONE",
      "w1d1_direction": "NONE",
      "flame": false,
      "retrace_flame": false,
      "daily_cloud_ok": false,
      "retrace_daily_cloud_ok": false
    },
    {
      "pair": "AUDCHF",
      "error": false,
      "w1_state": 1,
      "d1_state": 1,
      "h1_state": 0,
      "d1_ribbon_state": 0,
      "chg_cc_d1": -0.3736486976710552,
      "aligned": false,
      "aligned_w1_d1": true,
      "double_aligned": false,
      "direction": "NONE",
      "w1d1_direction": "BULL",
      "flame": false,
      "retrace_flame": false,
      "daily_cloud_ok": false,
      "retrace_daily_cloud_ok": false
    },
    {
      "pair": "AUDJPY",
      "error": false,
      "w1_state": 1,
      "d1_state": 0,
      "h1_state": 0,
      "d1_ribbon_state": 0,
      "chg_cc_d1": -0.32863638409939666,
      "aligned": false,
      "aligned_w1_d1": false,
      "double_aligned": false,
      "direction": "NONE",
      "w1d1_direction": "NONE",
      "flame": false,
      "retrace_flame": false,
      "daily_cloud_ok": false,
      "retrace_daily_cloud_ok": false
    },
    {
      "pair": "AUDNZD",
      "error": false,
      "w1_state": 1,
      "d1_state": 0,
      "h1_state": -1,
      "d1_ribbon_state": 0,
      "chg_cc_d1": -0.13789184265288454,
      "aligned": false,
      "aligned_w1_d1": false,
      "double_aligned": false,
      "direction": "NONE",
      "w1d1_direction": "NONE",
      "flame": false,
      "retrace_flame": false,
      "daily_cloud_ok": false,
      "retrace_daily_cloud_ok": false
    },
    {
      "pair": "AUDUSD",
      "error": false,
      "w1_state": 0,
      "d1_state": -1,
      "h1_state": 0,
      "d1_ribbon_state": 0,
      "chg_cc_d1": -0.46215730465295707,
      "aligned": false,
      "aligned_w1_d1": false,
      "double_aligned": false,
      "direction": "NONE",
      "w1d1_direction": "NONE",
      "flame": false,
      "retrace_flame": false,
      "daily_cloud_ok": false,
      "retrace_daily_cloud_ok": false
    },
    {
      "pair": "CADCHF",
      "error": false,
      "w1_state": 1,
      "d1_state": 0,
      "h1_state": 0,
      "d1_ribbon_state": 0,
      "chg_cc_d1": 0.06981777560568089,
      "aligned": false,
      "aligned_w1_d1": false,
      "double_aligned": false,
      "direction": "NONE",
      "w1d1_direction": "NONE",
      "flame": false,
      "retrace_flame": false,
      "daily_cloud_ok": false,
      "retrace_daily_cloud_ok": false
    },
    {
      "pair": "CADJPY",
      "error": false,
      "w1_state": 1,
      "d1_state": 1,
      "h1_state": 1,
      "d1_ribbon_state": 1,
      "chg_cc_d1": 0.11176572517761643,
      "aligned": true,
      "aligned_w1_d1": true,
      "double_aligned": true,
      "direction": "BULL",
      "w1d1_direction": "BULL",
      "flame": true,
      "retrace_flame": true,
      "daily_cloud_ok": true,
      "retrace_daily_cloud_ok": true
    },
    {
      "pair": "CHFJPY",
      "error": false,
      "w1_state": 1,
      "d1_state": 0,
      "h1_state": 1,
      "d1_ribbon_state": 0,
      "chg_cc_d1": 0.04666077615733323,
      "aligned": false,
      "aligned_w1_d1": false,
      "double_aligned": false,
      "direction": "NONE",
      "w1d1_direction": "NONE",
      "flame": false,
      "retrace_flame": false,
      "daily_cloud_ok": false,
      "retrace_daily_cloud_ok": false
    },
    {
      "pair": "EURAUD",
      "error": false,
      "w1_state": -1,
      "d1_state": 0,
      "h1_state": 1,
      "d1_ribbon_state": 0,
      "chg_cc_d1": 0.3513856185473607,
      "aligned": false,
      "aligned_w1_d1": false,
      "double_aligned": false,
      "direction": "NONE",
      "w1d1_direction": "NONE",
      "flame": false,
      "retrace_flame": false,
      "daily_cloud_ok": false,
      "retrace_daily_cloud_ok": false
    },
    {
      "pair": "EURCAD",
      "error": false,
      "w1_state": -1,
      "d1_state": -1,
      "h1_state": -1,
      "d1_ribbon_state": 0,
      "chg_cc_d1": -0.0847026935456524,
      "aligned": true,
      "aligned_w1_d1": true,
      "double_aligned": true,
      "direction": "BEAR",
      "w1d1_direction": "BEAR",
      "flame": false,
      "retrace_flame": true,
      "daily_cloud_ok": false,
      "retrace_daily_cloud_ok": false
    },
    {
      "pair": "EURCHF",
      "error": false,
      "w1_state": 0,
      "d1_state": 1,
      "h1_state": 0,
      "d1_ribbon_state": 0,
      "chg_cc_d1": -0.021901966796615924,
      "aligned": false,
      "aligned_w1_d1": false,
      "double_aligned": false,
      "direction": "NONE",
      "w1d1_direction": "NONE",
      "flame": false,
      "retrace_flame": false,
      "daily_cloud_ok": false,
      "retrace_daily_cloud_ok": false
    },
    {
      "pair": "EURGBP",
      "error": false,
      "w1_state": 0,
      "d1_state": 0,
      "h1_state": -1,
      "d1_ribbon_state": -1,
      "chg_cc_d1": 0.002312673450511101,
      "aligned": false,
      "aligned_w1_d1": false,
      "double_aligned": false,
      "direction": "NONE",
      "w1d1_direction": "NONE",
      "flame": false,
      "retrace_flame": false,
      "daily_cloud_ok": false,
      "retrace_daily_cloud_ok": false
    },
    {
      "pair": "EURJPY",
      "error": false,
      "w1_state": 0,
      "d1_state": 1,
      "h1_state": 0,
      "d1_ribbon_state": 1,
      "chg_cc_d1": 0.028267629215693382,
      "aligned": false,
      "aligned_w1_d1": false,
      "double_aligned": false,
      "direction": "NONE",
      "w1d1_direction": "NONE",
      "flame": false,
      "retrace_flame": false,
      "daily_cloud_ok": false,
      "retrace_daily_cloud_ok": false
    },
    {
      "pair": "EURNZD",
      "error": false,
      "w1_state": -1,
      "d1_state": 0,
      "h1_state": 0,
      "d1_ribbon_state": 0,
      "chg_cc_d1": 0.21139729068388366,
      "aligned": false,
      "aligned_w1_d1": false,
      "double_aligned": false,
      "direction": "NONE",
      "w1d1_direction": "NONE",
      "flame": false,
      "retrace_flame": false,
      "daily_cloud_ok": false,
      "retrace_daily_cloud_ok": false
    },
    {
      "pair": "EURUSD",
      "error": false,
      "w1_state": -1,
      "d1_state": 0,
      "h1_state": -1,
      "d1_ribbon_state": -1,
      "chg_cc_d1": -0.10507096596389684,
      "aligned": false,
      "aligned_w1_d1": false,
      "double_aligned": false,
      "direction": "NONE",
      "w1d1_direction": "NONE",
      "flame": false,
      "retrace_flame": false,
      "daily_cloud_ok": false,
      "retrace_daily_cloud_ok": false
    },
    {
      "pair": "GBPAUD",
      "error": false,
      "w1_state": -1,
      "d1_state": 1,
      "h1_state": 1,
      "d1_ribbon_state": 0,
      "chg_cc_d1": 0.3529583759737619,
      "aligned": true,
      "aligned_w1_d1": false,
      "double_aligned": false,
      "direction": "BULL",
      "w1d1_direction": "NONE",
      "flame": false,
      "retrace_flame": false,
      "daily_cloud_ok": false,
      "retrace_daily_cloud_ok": false
    },
    {
      "pair": "GBPCAD",
      "error": false,
      "w1_state": -1,
      "d1_state": 0,
      "h1_state": -1,
      "d1_ribbon_state": 0,
      "chg_cc_d1": -0.08247601684246895,
      "aligned": false,
      "aligned_w1_d1": false,
      "double_aligned": false,
      "direction": "NONE",
      "w1d1_direction": "NONE",
      "flame": false,
      "retrace_flame": false,
      "daily_cloud_ok": false,
      "retrace_daily_cloud_ok": false
    },
    {
      "pair": "GBPCHF",
      "error": false,
      "w1_state": -1,
      "d1_state": 1,
      "h1_state": 0,
      "d1_ribbon_state": 0,
      "chg_cc_d1": -0.022729425134957664,
      "aligned": false,
      "aligned_w1_d1": false,
      "double_aligned": false,
      "direction": "NONE",
      "w1d1_direction": "NONE",
      "flame": false,
      "retrace_flame": false,
      "daily_cloud_ok": false,
      "retrace_daily_cloud_ok": false
    },
    {
      "pair": "GBPJPY",
      "error": false,
      "w1_state": 0,
      "d1_state": 1,
      "h1_state": 0,
      "d1_ribbon_state": 1,
      "chg_cc_d1": 0.025385960623555373,
      "aligned": false,
      "aligned_w1_d1": false,
      "double_aligned": false,
      "direction": "NONE",
      "w1d1_direction": "NONE",
      "flame": false,
      "retrace_flame": false,
      "daily_cloud_ok": false,
      "retrace_daily_cloud_ok": false
    },
    {
      "pair": "GBPNZD",
      "error": false,
      "w1_state": -1,
      "d1_state": 1,
      "h1_state": 0,
      "d1_ribbon_state": 0,
      "chg_cc_d1": 0.2172945519281709,
      "aligned": false,
      "aligned_w1_d1": false,
      "double_aligned": false,
      "direction": "NONE",
      "w1d1_direction": "NONE",
      "flame": false,
      "retrace_flame": false,
      "daily_cloud_ok": false,
      "retrace_daily_cloud_ok": false
    },
    {
      "pair": "GBPUSD",
      "error": false,
      "w1_state": -1,
      "d1_state": -1,
      "h1_state": -1,
      "d1_ribbon_state": 0,
      "chg_cc_d1": -0.09458694551196892,
      "aligned": true,
      "aligned_w1_d1": true,
      "double_aligned": true,
      "direction": "BEAR",
      "w1d1_direction": "BEAR",
      "flame": false,
      "retrace_flame": true,
      "daily_cloud_ok": false,
      "retrace_daily_cloud_ok": false
    },
    {
      "pair": "NZDCAD",
      "error": false,
      "w1_state": 1,
      "d1_state": -1,
      "h1_state": -1,
      "d1_ribbon_state": -1,
      "chg_cc_d1": -0.2996766973389733,
      "aligned": true,
      "aligned_w1_d1": false,
      "double_aligned": false,
      "direction": "BEAR",
      "w1d1_direction": "NONE",
      "flame": true,
      "retrace_flame": false,
      "daily_cloud_ok": true,
      "retrace_daily_cloud_ok": false
    },
    {
      "pair": "NZDCHF",
      "error": false,
      "w1_state": 0,
      "d1_state": 0,
      "h1_state": -1,
      "d1_ribbon_state": -1,
      "chg_cc_d1": -0.23008465378771553,
      "aligned": false,
      "aligned_w1_d1": false,
      "double_aligned": false,
      "direction": "NONE",
      "w1d1_direction": "NONE",
      "flame": false,
      "retrace_flame": false,
      "daily_cloud_ok": false,
      "retrace_daily_cloud_ok": false
    },
    {
      "pair": "NZDJPY",
      "error": false,
      "w1_state": 0,
      "d1_state": 0,
      "h1_state": 0,
      "d1_ribbon_state": 0,
      "chg_cc_d1": -0.17239893112663862,
      "aligned": false,
      "aligned_w1_d1": false,
      "double_aligned": false,
      "direction": "NONE",
      "w1d1_direction": "NONE",
      "flame": false,
      "retrace_flame": false,
      "daily_cloud_ok": false,
      "retrace_daily_cloud_ok": false
    },
    {
      "pair": "NZDUSD",
      "error": false,
      "w1_state": 0,
      "d1_state": -1,
      "h1_state": 0,
      "d1_ribbon_state": 0,
      "chg_cc_d1": -0.3055389604847586,
      "aligned": false,
      "aligned_w1_d1": false,
      "double_aligned": false,
      "direction": "NONE",
      "w1d1_direction": "NONE",
      "flame": false,
      "retrace_flame": false,
      "daily_cloud_ok": false,
      "retrace_daily_cloud_ok": false
    },
    {
      "pair": "USDCAD",
      "error": false,
      "w1_state": 1,
      "d1_state": 0,
      "h1_state": 1,
      "d1_ribbon_state": 0,
      "chg_cc_d1": 0.011655436168287018,
      "aligned": false,
      "aligned_w1_d1": false,
      "double_aligned": false,
      "direction": "NONE",
      "w1d1_direction": "NONE",
      "flame": false,
      "retrace_flame": false,
      "daily_cloud_ok": false,
      "retrace_daily_cloud_ok": false
    },
    {
      "pair": "USDCHF",
      "error": false,
      "w1_state": -1,
      "d1_state": 0,
      "h1_state": 0,
      "d1_ribbon_state": 0,
      "chg_cc_d1": 0.08265408629085698,
      "aligned": false,
      "aligned_w1_d1": false,
      "double_aligned": false,
      "direction": "NONE",
      "w1d1_direction": "NONE",
      "flame": false,
      "retrace_flame": false,
      "daily_cloud_ok": false,
      "retrace_daily_cloud_ok": false
    },
    {
      "pair": "USDJPY",
      "error": false,
      "w1_state": 0,
      "d1_state": 1,
      "h1_state": 1,
      "d1_ribbon_state": 1,
      "chg_cc_d1": 0.1205587360899851,
      "aligned": true,
      "aligned_w1_d1": false,
      "double_aligned": false,
      "direction": "BULL",
      "w1d1_direction": "NONE",
      "flame": true,
      "retrace_flame": false,
      "daily_cloud_ok": true,
      "retrace_daily_cloud_ok": false
    },
    {
      "pair": "XAUUSD",
      "error": false,
      "w1_state": -1,
      "d1_state": 0,
      "h1_state": -1,
      "d1_ribbon_state": 0,
      "chg_cc_d1": 0.23862448811473783,
      "aligned": false,
      "aligned_w1_d1": false,
      "double_aligned": false,
      "direction": "NONE",
      "w1d1_direction": "NONE",
      "flame": false,
      "retrace_flame": false,
      "daily_cloud_ok": false,
      "retrace_daily_cloud_ok": false
    }
  ],
  "aligned_rows": [
    {
      "pair": "CADJPY",
      "error": false,
      "w1_state": 1,
      "d1_state": 1,
      "h1_state": 1,
      "d1_ribbon_state": 1,
      "chg_cc_d1": 0.11176572517761643,
      "aligned": true,
      "aligned_w1_d1": true,
      "double_aligned": true,
      "direction": "BULL",
      "w1d1_direction": "BULL",
      "flame": true,
      "retrace_flame": true,
      "daily_cloud_ok": true,
      "retrace_daily_cloud_ok": true
    },
    {
      "pair": "GBPAUD",
      "error": false,
      "w1_state": -1,
      "d1_state": 1,
      "h1_state": 1,
      "d1_ribbon_state": 0,
      "chg_cc_d1": 0.3529583759737619,
      "aligned": true,
      "aligned_w1_d1": false,
      "double_aligned": false,
      "direction": "BULL",
      "w1d1_direction": "NONE",
      "flame": false,
      "retrace_flame": false,
      "daily_cloud_ok": false,
      "retrace_daily_cloud_ok": false
    },
    {
      "pair": "USDJPY",
      "error": false,
      "w1_state": 0,
      "d1_state": 1,
      "h1_state": 1,
      "d1_ribbon_state": 1,
      "chg_cc_d1": 0.1205587360899851,
      "aligned": true,
      "aligned_w1_d1": false,
      "double_aligned": false,
      "direction": "BULL",
      "w1d1_direction": "NONE",
      "flame": true,
      "retrace_flame": false,
      "daily_cloud_ok": true,
      "retrace_daily_cloud_ok": false
    },
    {
      "pair": "EURCAD",
      "error": false,
      "w1_state": -1,
      "d1_state": -1,
      "h1_state": -1,
      "d1_ribbon_state": 0,
      "chg_cc_d1": -0.0847026935456524,
      "aligned": true,
      "aligned_w1_d1": true,
      "double_aligned": true,
      "direction": "BEAR",
      "w1d1_direction": "BEAR",
      "flame": false,
      "retrace_flame": true,
      "daily_cloud_ok": false,
      "retrace_daily_cloud_ok": false
    },
    {
      "pair": "GBPUSD",
      "error": false,
      "w1_state": -1,
      "d1_state": -1,
      "h1_state": -1,
      "d1_ribbon_state": 0,
      "chg_cc_d1": -0.09458694551196892,
      "aligned": true,
      "aligned_w1_d1": true,
      "double_aligned": true,
      "direction": "BEAR",
      "w1d1_direction": "BEAR",
      "flame": false,
      "retrace_flame": true,
      "daily_cloud_ok": false,
      "retrace_daily_cloud_ok": false
    },
    {
      "pair": "NZDCAD",
      "error": false,
      "w1_state": 1,
      "d1_state": -1,
      "h1_state": -1,
      "d1_ribbon_state": -1,
      "chg_cc_d1": -0.2996766973389733,
      "aligned": true,
      "aligned_w1_d1": false,
      "double_aligned": false,
      "direction": "BEAR",
      "w1d1_direction": "NONE",
      "flame": true,
      "retrace_flame": false,
      "daily_cloud_ok": true,
      "retrace_daily_cloud_ok": false
    }
  ],
  "telegram_rows": [],
  "retracing_rows": [],
  "exited_rows": [
    {
      "pair": "GBPUSD",
      "direction": "BEAR",
      "chg_cc_d1": -0.17576786725058388,
      "flame": false,
      "daily_cloud_ok": false,
      "section": "ALIGNED"
    }
  ]
}