{
  "generated_at": "2026-06-18T16:18:46.608291+00:00",
  "runtime_seconds": 39.59,
  "source": "S&P MidCap 400 (Wikipedia)",
  "benchmark": "IWR",
  "themes": [
    {
      "theme": "Distributors",
      "stocks": 3,
      "avg_score": 83.38,
      "median_21d": 11.3,
      "median_63d": 63.31,
      "median_rel_63d": 51.68,
      "pct_above_sma50": 100.0,
      "pct_above_sma200": 0.0,
      "news_score": 72.0,
      "news_hits": 8,
      "news_sources": 5,
      "final_score": 79.04
    },
    {
      "theme": "Semis",
      "stocks": 15,
      "avg_score": 70.01,
      "median_21d": 14.57,
      "median_63d": 57.26,
      "median_rel_63d": 45.63,
      "pct_above_sma50": 86.7,
      "pct_above_sma200": 0.0,
      "news_score": 100.0,
      "news_hits": 12,
      "news_sources": 12,
      "final_score": 73.14
    },
    {
      "theme": "Hardware",
      "stocks": 10,
      "avg_score": 53.67,
      "median_21d": 10.86,
      "median_63d": 22.47,
      "median_rel_63d": 10.84,
      "pct_above_sma50": 70.0,
      "pct_above_sma200": 0.0,
      "news_score": 100.0,
      "news_hits": 12,
      "news_sources": 7,
      "final_score": 57.82
    },
    {
      "theme": "Logiciels",
      "stocks": 19,
      "avg_score": 25.13,
      "median_21d": -4.97,
      "median_63d": -9.13,
      "median_rel_63d": -20.76,
      "pct_above_sma50": 42.1,
      "pct_above_sma200": 0.0,
      "news_score": 100.0,
      "news_hits": 12,
      "news_sources": 8,
      "final_score": 34.69
    }
  ],
  "stocks": [
    {
      "ticker": "ALGM",
      "name": "Allegro MicroSystems",
      "theme": "Semis",
      "sector": "Technology",
      "industry": "Semiconductors",
      "close": 58.43000030517578,
      "perf_5d": 21.830695205523586,
      "perf_21d": 40.28811083925352,
      "perf_63d": 89.03267743001216,
      "perf_126d": 122.67530798338075,
      "perf_ytd": 117.13118036600396,
      "rel_63d_vs_qqq": 77.403976462149,
      "rsi14": 64.18592728889841,
      "vol_21d": 95.02629014976581,
      "volume_ratio": 0.47254573551480245,
      "above_sma50": true,
      "above_sma200": false,
      "near_20d_high": true,
      "score": 100.0,
      "market_cap": 10856765440.0
    },
    {
      "ticker": "AMKR",
      "name": "Amkor Technology",
      "theme": "Semis",
      "sector": "Technology",
      "industry": "Semiconductor Equipment & Materials",
      "close": 89.87000274658203,
      "perf_5d": 18.017072811273028,
      "perf_21d": 37.276658457645695,
      "perf_63d": 86.93354998341243,
      "perf_126d": 123.79228126971098,
      "perf_ytd": 110.02686973793536,
      "rel_63d_vs_qqq": 75.30484901554928,
      "rsi14": 73.3124000487129,
      "vol_21d": 82.36204514091224,
      "volume_ratio": 0.34235403146086735,
      "above_sma50": true,
      "above_sma200": false,
      "near_20d_high": true,
      "score": 100.0,
      "market_cap": 22276302848.0
    },
    {
      "ticker": "DOCN",
      "name": "DigitalOcean",
      "theme": "Logiciels",
      "sector": "Technology",
      "industry": "Software - Infrastructure",
      "close": 175.14999389648438,
      "perf_5d": 0.22889493361051283,
      "perf_21d": 16.751092459898388,
      "perf_63d": 105.2138219423536,
      "perf_126d": 294.12691113634975,
      "perf_ytd": 257.66793859591724,
      "rel_63d_vs_qqq": 93.58512097449045,
      "rsi14": 63.24869117830699,
      "vol_21d": 65.05518943186954,
      "volume_ratio": 0.40215672762176663,
      "above_sma50": true,
      "above_sma200": false,
      "near_20d_high": false,
      "score": 100.0,
      "market_cap": 18279387136.0
    },
    {
      "ticker": "FLEX",
      "name": "Flex Ltd.",
      "theme": "Hardware",
      "sector": "Technology",
      "industry": "Electronic Components",
      "close": 145.22000122070312,
      "perf_5d": -4.454243060584284,
      "perf_21d": 14.989310450506421,
      "perf_63d": 120.73263292268659,
      "perf_126d": 123.3810128422856,
      "perf_ytd": 128.04648323611886,
      "rel_63d_vs_qqq": 109.10393195482344,
      "rsi14": 45.559107814303,
      "vol_21d": 62.62453861700587,
      "volume_ratio": 0.28134333627985897,
      "above_sma50": true,
      "above_sma200": false,
      "near_20d_high": false,
      "score": 100.0,
      "market_cap": 53205401600.0
    },
    {
      "ticker": "MKSI",
      "name": "MKS Instruments",
      "theme": "Semis",
      "sector": "Technology",
      "industry": "Scientific & Technical Instruments",
      "close": 399.114990234375,
      "perf_5d": 15.578298902226217,
      "perf_21d": 35.8374064197617,
      "perf_63d": 68.63682780899715,
      "perf_126d": 155.8731758701081,
      "perf_ytd": 137.46843418581648,
      "rel_63d_vs_qqq": 57.00812684113401,
      "rsi14": 70.50002990619451,
      "vol_21d": 64.18080176529993,
      "volume_ratio": 0.6446060094667828,
      "above_sma50": true,
      "above_sma200": false,
      "near_20d_high": true,
      "score": 100.0,
      "market_cap": 26957873152.0
    },
    {
      "ticker": "TTMI",
      "name": "TTM Technologies",
      "theme": "Hardware",
      "sector": "Technology",
      "industry": "Electronic Components",
      "close": 215.58999633789062,
      "perf_5d": 15.159440524672153,
      "perf_21d": 33.566688214195175,
      "perf_63d": 122.07456970702904,
      "perf_126d": 218.7786560600442,
      "perf_ytd": 205.32501695841185,
      "rel_63d_vs_qqq": 110.44586873916589,
      "rsi14": 68.19326555482328,
      "vol_21d": 81.1751280170154,
      "volume_ratio": 0.3638286849053673,
      "above_sma50": true,
      "above_sma200": false,
      "near_20d_high": true,
      "score": 100.0,
      "market_cap": 22389032960.0
    },
    {
      "ticker": "SNX",
      "name": "TD Synnex",
      "theme": "Distributors",
      "sector": "Technology",
      "industry": "Electronics & Computer Distribution",
      "close": 280.95001220703125,
      "perf_5d": 1.3930549352758392,
      "perf_21d": 24.171315755310417,
      "perf_63d": 81.29808687377644,
      "perf_126d": 87.52877248531534,
      "perf_ytd": 84.13093095507607,
      "rel_63d_vs_qqq": 69.66938590591329,
      "rsi14": 65.98928634686456,
      "vol_21d": 33.887503413874455,
      "volume_ratio": 0.358109717356182,
      "above_sma50": true,
      "above_sma200": false,
      "near_20d_high": true,
      "score": 95.72,
      "market_cap": 22622556160.0
    },
    {
      "ticker": "SITM",
      "name": "SiTime",
      "theme": "Semis",
      "sector": "Technology",
      "industry": "Semiconductors",
      "close": 709.385009765625,
      "perf_5d": -1.6436942805816424,
      "perf_21d": 2.2669661260413143,
      "perf_63d": 99.02506083737504,
      "perf_126d": 95.10038444929663,
      "perf_ytd": 91.746412085146,
      "rel_63d_vs_qqq": 87.39635986951188,
      "rsi14": 49.8990646643781,
      "vol_21d": 73.81743412835303,
      "volume_ratio": 0.42833290648909944,
      "above_sma50": true,
      "above_sma200": false,
      "near_20d_high": false,
      "score": 93.03,
      "market_cap": 18725513216.0
    },
    {
      "ticker": "SYNA",
      "name": "Synaptics",
      "theme": "Semis",
      "sector": "Technology",
      "industry": "Semiconductors",
      "close": 141.64999389648438,
      "perf_5d": 4.093174596179772,
      "perf_21d": 14.566478967763397,
      "perf_63d": 95.37930192618535,
      "perf_126d": 92.01572501331809,
      "perf_ytd": 87.02138617862715,
      "rel_63d_vs_qqq": 83.7506009583222,
      "rsi14": 52.621473543613604,
      "vol_21d": 86.91712037376863,
      "volume_ratio": 0.26094027854276497,
      "above_sma50": true,
      "above_sma200": false,
      "near_20d_high": false,
      "score": 92.38,
      "market_cap": 5473027584.0
    },
    {
      "ticker": "ONTO",
      "name": "Onto Innovation",
      "theme": "Semis",
      "sector": "Technology",
      "industry": "Semiconductor Equipment & Materials",
      "close": 338.5199890136719,
      "perf_5d": 11.527687666818377,
      "perf_21d": 36.45597650559833,
      "perf_63d": 61.61557250215648,
      "perf_126d": 119.46190535732373,
      "perf_ytd": 104.08753781810071,
      "rel_63d_vs_qqq": 49.986871534293336,
      "rsi14": 71.36925051757547,
      "vol_21d": 79.43828662602922,
      "volume_ratio": 0.2733332758448224,
      "above_sma50": true,
      "above_sma200": false,
      "near_20d_high": true,
      "score": 92.32,
      "market_cap": 16839192576.0
    },
    {
      "ticker": "ENTG",
      "name": "Entegris",
      "theme": "Semis",
      "sector": "Technology",
      "industry": "Semiconductor Equipment & Materials",
      "close": 172.5500030517578,
      "perf_5d": 19.065695026163265,
      "perf_21d": 38.90677938827758,
      "perf_63d": 49.03272107709864,
      "perf_126d": 96.467532891725,
      "perf_ytd": 92.95760456379195,
      "rel_63d_vs_qqq": 37.404020109235496,
      "rsi14": 65.57196110078374,
      "vol_21d": 85.53765981328772,
      "volume_ratio": 0.4483694743600616,
      "above_sma50": true,
      "above_sma200": false,
      "near_20d_high": true,
      "score": 90.2,
      "market_cap": 26279364608.0
    },
    {
      "ticker": "CVLT",
      "name": "CommVault Systems",
      "theme": "Logiciels",
      "sector": "Technology",
      "industry": "Software - Application",
      "close": 129.0,
      "perf_5d": 1.7109501991775522,
      "perf_21d": 26.507794896259096,
      "perf_63d": 61.65412915627504,
      "perf_126d": 6.65564551870359,
      "perf_ytd": 3.8814621380084846,
      "rel_63d_vs_qqq": 50.025428188411894,
      "rsi14": 70.65698247608012,
      "vol_21d": 33.47229926556222,
      "volume_ratio": 0.44904287194248177,
      "above_sma50": true,
      "above_sma200": false,
      "near_20d_high": true,
      "score": 81.73,
      "market_cap": 5321331200.0
    },
    {
      "ticker": "AVT",
      "name": "Avnet",
      "theme": "Distributors",
      "sector": "Technology",
      "industry": "Electronics & Computer Distribution",
      "close": 90.66500091552734,
      "perf_5d": 2.457908356045202,
      "perf_21d": 10.567084574544449,
      "perf_63d": 51.78079252414991,
      "perf_126d": 87.36693615268814,
      "perf_ytd": 85.46821322836678,
      "rel_63d_vs_qqq": 40.15209155628676,
      "rsi14": 58.62052329154435,
      "vol_21d": 41.62843333894192,
      "volume_ratio": 0.5661517834556034,
      "above_sma50": true,
      "above_sma200": false,
      "near_20d_high": true,
      "score": 78.84,
      "market_cap": 7436713472.0
    },
    {
      "ticker": "LFUS",
      "name": "Littelfuse",
      "theme": "Hardware",
      "sector": "Technology",
      "industry": "Electronic Components",
      "close": 481.2200012207031,
      "perf_5d": 3.9396928164386003,
      "perf_21d": 12.055261662035432,
      "perf_63d": 44.85224647692021,
      "perf_126d": 90.82697651521075,
      "perf_ytd": 84.00185815001353,
      "rel_63d_vs_qqq": 33.22354550905706,
      "rsi14": 54.68923862810693,
      "vol_21d": 42.98619868900006,
      "volume_ratio": 0.6260094543405441,
      "above_sma50": true,
      "above_sma200": false,
      "near_20d_high": true,
      "score": 78.13,
      "market_cap": 12169526272.0
    },
    {
      "ticker": "LSCC",
      "name": "Lattice Semiconductor",
      "theme": "Semis",
      "sector": "Technology",
      "industry": "Semiconductors",
      "close": 149.27000427246094,
      "perf_5d": 4.486912806050292,
      "perf_21d": 20.146496167954766,
      "perf_63d": 57.258751740365234,
      "perf_126d": 100.36242184222944,
      "perf_ytd": 89.79021154035871,
      "rel_63d_vs_qqq": 45.63005077250209,
      "rsi14": 51.30032220854368,
      "vol_21d": 78.89666840313376,
      "volume_ratio": 0.3303826332608437,
      "above_sma50": true,
      "above_sma200": false,
      "near_20d_high": false,
      "score": 77.97,
      "market_cap": 20451164160.0
    },
    {
      "ticker": "MTSI",
      "name": "MACOM Technology Solutions",
      "theme": "Semis",
      "sector": "Technology",
      "industry": "Semiconductors",
      "close": 382.3450012207031,
      "perf_5d": 2.02395966950204,
      "perf_21d": 6.5087162291231015,
      "perf_63d": 70.27924318741665,
      "perf_126d": 117.62479134133864,
      "perf_ytd": 118.53279981064313,
      "rel_63d_vs_qqq": 58.65054221955351,
      "rsi14": 54.93106452421729,
      "vol_21d": 70.14996626502264,
      "volume_ratio": 0.2596105011294041,
      "above_sma50": true,
      "above_sma200": false,
      "near_20d_high": false,
      "score": 76.85,
      "market_cap": 29171308544.0
    },
    {
      "ticker": "ARW",
      "name": "Arrow Electronics",
      "theme": "Distributors",
      "sector": "Technology",
      "industry": "Electronics & Computer Distribution",
      "close": 229.57000732421875,
      "perf_5d": 3.010861839491308,
      "perf_21d": 11.295875584983728,
      "perf_63d": 63.31364826262353,
      "perf_126d": 103.59170182248208,
      "perf_ytd": 103.08740752379512,
      "rel_63d_vs_qqq": 51.684947294760384,
      "rsi14": 64.85089165292972,
      "vol_21d": 33.534629972286,
      "volume_ratio": 0.1994360541637852,
      "above_sma50": true,
      "above_sma200": false,
      "near_20d_high": true,
      "score": 75.58,
      "market_cap": 11738819584.0
    },
    {
      "ticker": "RMBS",
      "name": "Rambus",
      "theme": "Semis",
      "sector": "Technology",
      "industry": "Semiconductors",
      "close": 138.24000549316406,
      "perf_5d": -4.31231098144843,
      "perf_21d": 13.283624416963713,
      "perf_63d": 46.10019179919937,
      "perf_126d": 45.992187061887925,
      "perf_ytd": 39.242553578668684,
      "rel_63d_vs_qqq": 34.471490831336226,
      "rsi14": 46.53617293411196,
      "vol_21d": 101.87613726396188,
      "volume_ratio": 0.686859383991605,
      "above_sma50": true,
      "above_sma200": false,
      "near_20d_high": false,
      "score": 74.16,
      "market_cap": 14948854784.0
    },
    {
      "ticker": "OKTA",
      "name": "Okta, Inc.",
      "theme": "Logiciels",
      "sector": "Technology",
      "industry": "Software - Infrastructure",
      "close": 112.06999969482422,
      "perf_5d": -4.621276855468748,
      "perf_21d": 30.77013265532318,
      "perf_63d": 38.76918862109277,
      "perf_126d": 23.71123106884292,
      "perf_ytd": 33.99091405145847,
      "rel_63d_vs_qqq": 27.140487653229627,
      "rsi14": 40.553308722272014,
      "vol_21d": 125.78600378978295,
      "volume_ratio": 0.2553183549101851,
      "above_sma50": true,
      "above_sma200": false,
      "near_20d_high": false,
      "score": 64.41,
      "market_cap": 19651076096.0
    },
    {
      "ticker": "CGNX",
      "name": "Cognex",
      "theme": "Hardware",
      "sector": "Technology",
      "industry": "Scientific & Technical Instruments",
      "close": 66.42500305175781,
      "perf_5d": 6.947355335699501,
      "perf_21d": 9.668952219048244,
      "perf_63d": 32.36660824304429,
      "perf_126d": 80.86566445159778,
      "perf_ytd": 80.37592085340297,
      "rel_63d_vs_qqq": 20.737907275181144,
      "rsi14": 51.24056984536456,
      "vol_21d": 47.748893046563055,
      "volume_ratio": 0.24282480481077567,
      "above_sma50": true,
      "above_sma200": false,
      "near_20d_high": true,
      "score": 57.32,
      "market_cap": 11054412800.0
    },
    {
      "ticker": "BDC",
      "name": "Belden Inc.",
      "theme": "Hardware",
      "sector": "Technology",
      "industry": "Communication Equipment",
      "close": 127.31500244140625,
      "perf_5d": 13.601932169958575,
      "perf_21d": 24.922020269227787,
      "perf_63d": 11.454757165559904,
      "perf_126d": 5.630570709977678,
      "perf_ytd": 8.159032114824116,
      "rel_63d_vs_qqq": -0.1739438023032438,
      "rsi14": 75.25519072585931,
      "vol_21d": 46.655904100019974,
      "volume_ratio": 0.4173972921296057,
      "above_sma50": true,
      "above_sma200": false,
      "near_20d_high": true,
      "score": 52.88,
      "market_cap": 4963417600.0
    },
    {
      "ticker": "TWLO",
      "name": "Twilio",
      "theme": "Logiciels",
      "sector": "Technology",
      "industry": "Software - Infrastructure",
      "close": 184.35000610351562,
      "perf_5d": -10.778235185341634,
      "perf_21d": -5.919872939722759,
      "perf_63d": 44.758545985359824,
      "perf_126d": 34.072731711647734,
      "perf_ytd": 33.23937936563095,
      "rel_63d_vs_qqq": 33.12984501749668,
      "rsi14": 47.06541317831456,
      "vol_21d": 83.77624610783609,
      "volume_ratio": 0.36116675788932073,
      "above_sma50": true,
      "above_sma200": false,
      "near_20d_high": false,
      "score": 51.64,
      "market_cap": 27979511808.0
    },
    {
      "ticker": "AEIS",
      "name": "Advanced Energy",
      "theme": "Semis",
      "sector": "Industrials",
      "industry": "Electrical Equipment & Parts",
      "close": 368.44000244140625,
      "perf_5d": 8.237370460543803,
      "perf_21d": 21.69919426603535,
      "perf_63d": 12.432538848831886,
      "perf_126d": 71.34464202144248,
      "perf_ytd": 66.07285019594616,
      "rel_63d_vs_qqq": 0.8038378809687377,
      "rsi14": 67.99956825070905,
      "vol_21d": 71.06947357031127,
      "volume_ratio": 0.21299025044679398,
      "above_sma50": true,
      "above_sma200": false,
      "near_20d_high": true,
      "score": 51.45,
      "market_cap": 14741526528.0
    },
    {
      "ticker": "NOVT",
      "name": "Novanta",
      "theme": "Hardware",
      "sector": "Technology",
      "industry": "Scientific & Technical Instruments",
      "close": 156.2899932861328,
      "perf_5d": -3.7682471756537383,
      "perf_21d": 5.916234665206277,
      "perf_63d": 31.801307870449303,
      "perf_126d": 28.782129614460338,
      "perf_ytd": 40.62443237757445,
      "rel_63d_vs_qqq": 20.172606902586153,
      "rsi14": 47.5888260367576,
      "vol_21d": 47.0877010462156,
      "volume_ratio": 0.3479217525009966,
      "above_sma50": true,
      "above_sma200": false,
      "near_20d_high": false,
      "score": 50.32,
      "market_cap": 5566003200.0
    },
    {
      "ticker": "CXT",
      "name": "Crane NXT",
      "theme": "Hardware",
      "sector": "Industrials",
      "industry": "Specialty Industrial Machinery",
      "close": 46.810001373291016,
      "perf_5d": 14.142899997907076,
      "perf_21d": 24.000717874581934,
      "perf_63d": 13.140200525530577,
      "perf_126d": -2.534453794861813,
      "perf_ytd": -1.1254618819757645,
      "rel_63d_vs_qqq": 1.5114995576674293,
      "rsi14": 73.53810123165374,
      "vol_21d": 56.19365610543324,
      "volume_ratio": 0.17386120050783901,
      "above_sma50": true,
      "above_sma200": false,
      "near_20d_high": true,
      "score": 44.97,
      "market_cap": 2693558272.0
    },
    {
      "ticker": "QLYS",
      "name": "Qualys",
      "theme": "Logiciels",
      "sector": "Technology",
      "industry": "Software - Infrastructure",
      "close": 111.0999984741211,
      "perf_5d": 0.24361331643572015,
      "perf_21d": 11.00010244686407,
      "perf_63d": 15.022261814227278,
      "perf_126d": -22.61615044482923,
      "perf_ytd": -15.197310791182394,
      "rel_63d_vs_qqq": 3.39356084636413,
      "rsi14": 54.931875917294825,
      "vol_21d": 40.906651300581245,
      "volume_ratio": 0.3356366601254802,
      "above_sma50": true,
      "above_sma200": false,
      "near_20d_high": false,
      "score": 38.94,
      "market_cap": 3912609536.0
    },
    {
      "ticker": "SLAB",
      "name": "Silicon Labs",
      "theme": "Semis",
      "sector": "Technology",
      "industry": "Semiconductors",
      "close": 219.14999389648438,
      "perf_5d": 0.11420740382397376,
      "perf_21d": 1.242717868974763,
      "perf_63d": 6.497227717221965,
      "perf_126d": 63.13086189557464,
      "perf_ytd": 66.11082093747007,
      "rel_63d_vs_qqq": -5.131473250641183,
      "rsi14": 58.71760719790461,
      "vol_21d": 5.413042797499614,
      "volume_ratio": 0.2384733797772085,
      "above_sma50": true,
      "above_sma200": false,
      "near_20d_high": true,
      "score": 37.01,
      "market_cap": 7227966464.0
    },
    {
      "ticker": "DT",
      "name": "Dynatrace",
      "theme": "Logiciels",
      "sector": "Technology",
      "industry": "Software - Application",
      "close": 41.25,
      "perf_5d": 2.1798392157503788,
      "perf_21d": 3.2282305932999966,
      "perf_63d": 5.606755119590168,
      "perf_126d": -6.610817953346171,
      "perf_ytd": -2.5973990879675557,
      "rel_63d_vs_qqq": -6.02194584827298,
      "rsi14": 41.9082141739916,
      "vol_21d": 42.41065117096813,
      "volume_ratio": 0.4420236307613615,
      "above_sma50": true,
      "above_sma200": false,
      "near_20d_high": false,
      "score": 34.41,
      "market_cap": 12023374848.0
    },
    {
      "ticker": "CRUS",
      "name": "Cirrus Logic",
      "theme": "Semis",
      "sector": "Technology",
      "industry": "Semiconductors",
      "close": 163.97999572753906,
      "perf_5d": 0.6444504381996952,
      "perf_21d": 1.7624403305496417,
      "perf_63d": 19.92101004832618,
      "perf_126d": 35.37521625173816,
      "perf_ytd": 37.02682229178167,
      "rel_63d_vs_qqq": 8.292309080463033,
      "rsi14": 44.511859153475484,
      "vol_21d": 45.28029809348932,
      "volume_ratio": 0.22918913551718223,
      "above_sma50": false,
      "above_sma200": false,
      "near_20d_high": false,
      "score": 28.6,
      "market_cap": 8273236992.0
    },
    {
      "ticker": "DBX",
      "name": "Dropbox",
      "theme": "Logiciels",
      "sector": "Technology",
      "industry": "Software - Infrastructure",
      "close": 26.049999237060547,
      "perf_5d": -3.446998965733472,
      "perf_21d": -5.37595863665522,
      "perf_63d": 3.496222320616593,
      "perf_126d": -8.884228408433327,
      "perf_ytd": -3.2677350840805697,
      "rel_63d_vs_qqq": -8.132478647246554,
      "rsi14": 43.95924437908313,
      "vol_21d": 38.13368202424045,
      "volume_ratio": 0.4389310672781445,
      "above_sma50": true,
      "above_sma200": false,
      "near_20d_high": false,
      "score": 28.22,
      "market_cap": 6076315648.0
    },
    {
      "ticker": "NTNX",
      "name": "Nutanix",
      "theme": "Logiciels",
      "sector": "Technology",
      "industry": "Software - Infrastructure",
      "close": 45.869998931884766,
      "perf_5d": -6.787238802533868,
      "perf_21d": -4.972035432191291,
      "perf_63d": 11.79624737164282,
      "perf_126d": -4.972035432191291,
      "perf_ytd": -9.347825464175541,
      "rel_63d_vs_qqq": 0.16754640377967256,
      "rsi14": 32.815966914488,
      "vol_21d": 59.21657397911658,
      "volume_ratio": 0.2764526495856764,
      "above_sma50": true,
      "above_sma200": false,
      "near_20d_high": false,
      "score": 28.22,
      "market_cap": 12394194944.0
    },
    {
      "ticker": "IPGP",
      "name": "IPG Photonics",
      "theme": "Semis",
      "sector": "Technology",
      "industry": "Semiconductor Equipment & Materials",
      "close": 116.86000061035156,
      "perf_5d": 5.099377681849804,
      "perf_21d": 3.1147963665959955,
      "perf_63d": -4.821630744260553,
      "perf_126d": 51.72683160701188,
      "perf_ytd": 56.14645420711586,
      "rel_63d_vs_qqq": -16.4503317121237,
      "rsi14": 51.93580755140973,
      "vol_21d": 69.81992621630764,
      "volume_ratio": 0.19106173057406345,
      "above_sma50": true,
      "above_sma200": false,
      "near_20d_high": false,
      "score": 26.44,
      "market_cap": 4959961088.0
    },
    {
      "ticker": "FN",
      "name": "Fabrinet",
      "theme": "Hardware",
      "sector": "Technology",
      "industry": "Electronic Components",
      "close": 578.0,
      "perf_5d": -0.7282203739850002,
      "perf_21d": -14.717816303946885,
      "perf_63d": 6.8885806749884315,
      "perf_126d": 28.11419348087554,
      "perf_ytd": 20.56234279154163,
      "rel_63d_vs_qqq": -4.740120292874717,
      "rsi14": 40.408548978696736,
      "vol_21d": 84.26665754681952,
      "volume_ratio": 0.560256150589611,
      "above_sma50": false,
      "above_sma200": false,
      "near_20d_high": false,
      "score": 22.11,
      "market_cap": 20709588992.0
    },
    {
      "ticker": "IDCC",
      "name": "InterDigital",
      "theme": "Logiciels",
      "sector": "Technology",
      "industry": "Software - Application",
      "close": 296.1549987792969,
      "perf_5d": 7.0465534804941,
      "perf_21d": 11.845231776958798,
      "perf_63d": -15.821414605864014,
      "perf_126d": -14.532916525570572,
      "perf_ytd": -8.822183090982517,
      "rel_63d_vs_qqq": -27.45011557372716,
      "rsi14": 80.74377553957815,
      "vol_21d": 41.434975136342366,
      "volume_ratio": 0.507217636022514,
      "above_sma50": false,
      "above_sma200": false,
      "near_20d_high": true,
      "score": 21.96,
      "market_cap": 7653229568.0
    },
    {
      "ticker": "P",
      "name": "Everpure",
      "theme": "Hardware",
      "sector": "Technology",
      "industry": "Computer Hardware",
      "close": 73.75,
      "perf_5d": 6.359971005218434,
      "perf_21d": -2.9988146993338183,
      "perf_63d": 12.681441464881127,
      "perf_126d": 5.780262060724373,
      "perf_ytd": 6.868566464340131,
      "rel_63d_vs_qqq": 1.0527404970179788,
      "rsi14": 42.2870863979133,
      "vol_21d": 90.86617989109544,
      "volume_ratio": 0.2165824866307064,
      "above_sma50": false,
      "above_sma200": false,
      "near_20d_high": false,
      "score": 18.94,
      "market_cap": 24554752000.0
    },
    {
      "ticker": "VNT",
      "name": "Vontier",
      "theme": "Hardware",
      "sector": "Technology",
      "industry": "Scientific & Technical Instruments",
      "close": 29.8700008392334,
      "perf_5d": 4.185562468594783,
      "perf_21d": 7.540476822239839,
      "perf_63d": -15.379981336620052,
      "perf_126d": -20.587453184299275,
      "perf_ytd": -20.86056678459729,
      "rel_63d_vs_qqq": -27.0086823044832,
      "rsi14": 66.03159673092722,
      "vol_21d": 23.931539512608595,
      "volume_ratio": 0.2725141057825276,
      "above_sma50": false,
      "above_sma200": false,
      "near_20d_high": true,
      "score": 11.98,
      "market_cap": 4205696000.0
    },
    {
      "ticker": "KD",
      "name": "Kyndryl",
      "theme": "IT / Internet",
      "sector": "Technology",
      "industry": "Information Technology Services",
      "close": 11.104999542236328,
      "perf_5d": -1.5514201673546335,
      "perf_21d": -7.689112313108959,
      "perf_63d": -10.22635695251326,
      "perf_126d": -58.110149202723235,
      "perf_ytd": -56.433897050014814,
      "rel_63d_vs_qqq": -21.85505792037641,
      "rsi14": 33.04347166782095,
      "vol_21d": 44.517066774119556,
      "volume_ratio": 0.5994405152117818,
      "above_sma50": false,
      "above_sma200": false,
      "near_20d_high": false,
      "score": 9.96,
      "market_cap": 2503591168.0
    },
    {
      "ticker": "OLED",
      "name": "Universal Display",
      "theme": "Semis",
      "sector": "Technology",
      "industry": "Electronic Components",
      "close": 87.91000366210938,
      "perf_5d": -1.6629381638048724,
      "perf_21d": 0.8850006916804043,
      "perf_63d": -7.333454931363059,
      "perf_126d": -24.260386923072875,
      "perf_ytd": -27.082361681621403,
      "rel_63d_vs_qqq": -18.962155899226207,
      "rsi14": 44.54178314575603,
      "vol_21d": 45.93645256959814,
      "volume_ratio": 0.288116539140671,
      "above_sma50": false,
      "above_sma200": false,
      "near_20d_high": false,
      "score": 9.76,
      "market_cap": 4109871104.0
    },
    {
      "ticker": "MANH",
      "name": "Manhattan Associates",
      "theme": "Logiciels",
      "sector": "Technology",
      "industry": "Software - Application",
      "close": 131.1300048828125,
      "perf_5d": -6.52932414405194,
      "perf_21d": -3.1679171054047495,
      "perf_63d": -6.208420590339758,
      "perf_126d": -25.299071494739877,
      "perf_ytd": -21.610469966693003,
      "rel_63d_vs_qqq": -17.837121558202906,
      "rsi14": 30.39784467208618,
      "vol_21d": 47.8982263330859,
      "volume_ratio": 0.33631834572080355,
      "above_sma50": false,
      "above_sma200": false,
      "near_20d_high": false,
      "score": 9.52,
      "market_cap": 7758254080.0
    },
    {
      "ticker": "DOCU",
      "name": "Docusign",
      "theme": "Logiciels",
      "sector": "Technology",
      "industry": "Software - Application",
      "close": 42.95000076293945,
      "perf_5d": -3.591466894549522,
      "perf_21d": -13.091860877630502,
      "perf_63d": -10.052354423163445,
      "perf_126d": -36.44569458534276,
      "perf_ytd": -33.77023627829537,
      "rel_63d_vs_qqq": -21.681055391026593,
      "rsi14": 27.061362859991476,
      "vol_21d": 55.54481399728548,
      "volume_ratio": 0.5818557381687849,
      "above_sma50": false,
      "above_sma200": false,
      "near_20d_high": false,
      "score": 8.55,
      "market_cap": 8199161344.0
    },
    {
      "ticker": "APPF",
      "name": "AppFolio",
      "theme": "Logiciels",
      "sector": "Technology",
      "industry": "Software - Application",
      "close": 151.57000732421875,
      "perf_5d": -5.078898874970039,
      "perf_21d": -5.162057077912429,
      "perf_63d": -9.130692715163324,
      "perf_126d": -34.40231588084276,
      "perf_ytd": -34.20583820079685,
      "rel_63d_vs_qqq": -20.759393683026474,
      "rsi14": 43.16630000566991,
      "vol_21d": 56.79843066916512,
      "volume_ratio": 0.32178779568049365,
      "above_sma50": false,
      "above_sma200": false,
      "near_20d_high": false,
      "score": 5.55,
      "market_cap": 5360176640.0
    },
    {
      "ticker": "PATH",
      "name": "UiPath",
      "theme": "Logiciels",
      "sector": "Technology",
      "industry": "Software - Infrastructure",
      "close": 10.175000190734863,
      "perf_5d": -4.460088683655384,
      "perf_21d": -3.5545023054059266,
      "perf_63d": -16.87091191991629,
      "perf_126d": -36.76196336705235,
      "perf_ytd": -35.92569195587131,
      "rel_63d_vs_qqq": -28.499612887779435,
      "rsi14": 33.85579806100168,
      "vol_21d": 60.65719267743509,
      "volume_ratio": 0.3582561342605155,
      "above_sma50": false,
      "above_sma200": false,
      "near_20d_high": false,
      "score": 3.2,
      "market_cap": 5269282816.0
    },
    {
      "ticker": "DLB",
      "name": "Dolby",
      "theme": "Logiciels",
      "sector": "Industrials",
      "industry": "Specialty Business Services",
      "close": 51.58000183105469,
      "perf_5d": -2.18091735476027,
      "perf_21d": -3.353938798302436,
      "perf_63d": -15.616218270945359,
      "perf_126d": -21.876297113232614,
      "perf_ytd": -17.855125897182667,
      "rel_63d_vs_qqq": -27.244919238808507,
      "rsi14": 23.52942019000912,
      "vol_21d": 23.343648616341248,
      "volume_ratio": 0.21823202726338378,
      "above_sma50": false,
      "above_sma200": false,
      "near_20d_high": false,
      "score": 1.04,
      "market_cap": 4879370752.0
    },
    {
      "ticker": "BILL",
      "name": "Bill Holdings",
      "theme": "Logiciels",
      "sector": "Technology",
      "industry": "Software - Application",
      "close": 32.25,
      "perf_5d": 0.3734793896531974,
      "perf_21d": -14.569536423841056,
      "perf_63d": -21.09126292430574,
      "perf_126d": -40.50913015189968,
      "perf_ytd": -36.21440046669681,
      "rel_63d_vs_qqq": -32.71996389216889,
      "rsi14": 33.56305647987267,
      "vol_21d": 58.243299518889636,
      "volume_ratio": 0.3421280605325148,
      "above_sma50": false,
      "above_sma200": false,
      "near_20d_high": false,
      "score": 0.0,
      "market_cap": 3211994368.0
    },
    {
      "ticker": "BLKB",
      "name": "Blackbaud",
      "theme": "Logiciels",
      "sector": "Technology",
      "industry": "Software - Application",
      "close": 26.850000381469727,
      "perf_5d": -1.864035882692483,
      "perf_21d": -14.599236878560918,
      "perf_63d": -39.37683489174063,
      "perf_126d": -57.292825134990345,
      "perf_ytd": -54.88911260925996,
      "rel_63d_vs_qqq": -51.005535859603775,
      "rsi14": 33.81113003806976,
      "vol_21d": 52.35733010040667,
      "volume_ratio": 0.39872150790979466,
      "above_sma50": false,
      "above_sma200": false,
      "near_20d_high": false,
      "score": 0.0,
      "market_cap": 1231899008.0
    },
    {
      "ticker": "BSY",
      "name": "Bentley Systems",
      "theme": "Logiciels",
      "sector": "Technology",
      "industry": "Software - Application",
      "close": 28.700000762939453,
      "perf_5d": -6.1171048431556745,
      "perf_21d": -12.88359534720428,
      "perf_63d": -24.10365840249066,
      "perf_126d": -28.588837715938688,
      "perf_ytd": -24.48949461628065,
      "rel_63d_vs_qqq": -35.732359370353805,
      "rsi14": 31.555348244704916,
      "vol_21d": 42.871940835003095,
      "volume_ratio": 0.4190169750086974,
      "above_sma50": false,
      "above_sma200": false,
      "near_20d_high": false,
      "score": 0.0,
      "market_cap": 8711369728.0
    },
    {
      "ticker": "GWRE",
      "name": "Guidewire Software",
      "theme": "Logiciels",
      "sector": "Technology",
      "industry": "Software - Application",
      "close": 107.6500015258789,
      "perf_5d": -9.171443996850137,
      "perf_21d": -23.11263070535802,
      "perf_63d": -31.006856137870685,
      "perf_126d": -44.39278704360976,
      "perf_ytd": -42.626446344168926,
      "rel_63d_vs_qqq": -42.63555710573383,
      "rsi14": 26.16980887179217,
      "vol_21d": 84.04188474119745,
      "volume_ratio": 0.48195219174276616,
      "above_sma50": false,
      "above_sma200": false,
      "near_20d_high": false,
      "score": 0.0,
      "market_cap": 8962547712.0
    },
    {
      "ticker": "PEGA",
      "name": "Pegasystems",
      "theme": "Logiciels",
      "sector": "Technology",
      "industry": "Software - Application",
      "close": 29.719999313354492,
      "perf_5d": -9.417866292599243,
      "perf_21d": -11.283584139240322,
      "perf_63d": -31.091374082800883,
      "perf_126d": -49.030643229984605,
      "perf_ytd": -46.947979201704214,
      "rel_63d_vs_qqq": -42.72007505066403,
      "rsi14": 24.68407833208721,
      "vol_21d": 47.14870449281812,
      "volume_ratio": 0.3601226748097142,
      "above_sma50": false,
      "above_sma200": false,
      "near_20d_high": false,
      "score": 0.0,
      "market_cap": 4966688768.0
    }
  ],
  "renko": {
    "STOCK:SNX": {
      "ticker": "SNX",
      "name": "TD Synnex",
      "asset_type": "STOCK",
      "theme": "Distributors",
      "tv_symbol": "NYSE:SNX",
      "renko_status": "BULL CONFIRMED",
      "final_action": "VALIDATED",
      "aligned": 1,
      "bias": "BULL",
      "px_3m": 1,
      "px_m": 1,
      "px_w": 1,
      "streak_3m": 7,
      "streak_m": 9,
      "streak_w": 17,
      "pnl_pct": 0.0,
      "roc14": 83.21797048452397,
      "roc21": 83.11035697970371,
      "close": 280.58,
      "reason": "3M/M/W bullish + ROC14/ROC21 positive"
    },
    "STOCK:AVT": {
      "ticker": "AVT",
      "name": "Avnet",
      "asset_type": "STOCK",
      "theme": "Distributors",
      "tv_symbol": "NASDAQ:AVT",
      "renko_status": "BULL CONFIRMED",
      "final_action": "VALIDATED",
      "aligned": 1,
      "bias": "BULL",
      "px_3m": 1,
      "px_m": 1,
      "px_w": 1,
      "streak_3m": 2,
      "streak_m": 8,
      "streak_w": 7,
      "pnl_pct": 0.0,
      "roc14": 51.749539594843476,
      "roc21": 78.31988982884124,
      "close": 90.64,
      "reason": "3M/M/W bullish + ROC14/ROC21 positive"
    },
    "STOCK:ARW": {
      "ticker": "ARW",
      "name": "Arrow Electronics",
      "asset_type": "STOCK",
      "theme": "Distributors",
      "tv_symbol": "NYSE:ARW",
      "renko_status": "BULL CONFIRMED",
      "final_action": "VALIDATED",
      "aligned": 1,
      "bias": "BULL",
      "px_3m": 1,
      "px_m": 1,
      "px_w": 1,
      "streak_3m": 6,
      "streak_m": 6,
      "streak_w": 13,
      "pnl_pct": 0.0,
      "roc14": 63.557391056679,
      "roc21": 96.89696554088805,
      "close": 229.7,
      "reason": "3M/M/W bullish + ROC14/ROC21 positive"
    },
    "STOCK:ALGM": {
      "ticker": "ALGM",
      "name": "Allegro MicroSystems",
      "asset_type": "STOCK",
      "theme": "Semis",
      "tv_symbol": "NASDAQ:ALGM",
      "renko_status": "BULL CONFIRMED",
      "final_action": "VALIDATED",
      "aligned": 1,
      "bias": "BULL",
      "px_3m": 1,
      "px_m": 1,
      "px_w": 1,
      "streak_3m": 1,
      "streak_m": 2,
      "streak_w": 4,
      "pnl_pct": 0.0,
      "roc14": 87.11853517507228,
      "roc21": 76.56865716883902,
      "close": 58.25,
      "reason": "3M/M/W bullish + ROC14/ROC21 positive"
    },
    "STOCK:AMKR": {
      "ticker": "AMKR",
      "name": "Amkor Technology",
      "asset_type": "STOCK",
      "theme": "Semis",
      "tv_symbol": "NASDAQ:AMKR",
      "renko_status": "BULL CONFIRMED",
      "final_action": "VALIDATED",
      "aligned": 1,
      "bias": "BULL",
      "px_3m": 1,
      "px_m": 1,
      "px_w": 1,
      "streak_3m": 1,
      "streak_m": 6,
      "streak_w": 6,
      "pnl_pct": 0.0,
      "roc14": 108.83926494533611,
      "roc21": 80.60752363709514,
      "close": 89.78,
      "reason": "3M/M/W bullish + ROC14/ROC21 positive"
    },
    "STOCK:MKSI": {
      "ticker": "MKSI",
      "name": "MKS Instruments",
      "asset_type": "STOCK",
      "theme": "Semis",
      "tv_symbol": "NASDAQ:MKSI",
      "renko_status": "BULL CONFIRMED",
      "final_action": "VALIDATED",
      "aligned": 1,
      "bias": "BULL",
      "px_3m": 1,
      "px_m": 1,
      "px_w": 1,
      "streak_3m": 2,
      "streak_m": 11,
      "streak_w": 13,
      "pnl_pct": 0.0,
      "roc14": 86.79315999063012,
      "roc21": 83.68653828434533,
      "close": 398.71,
      "reason": "3M/M/W bullish + ROC14/ROC21 positive"
    },
    "STOCK:FLEX": {
      "ticker": "FLEX",
      "name": "Flex Ltd.",
      "asset_type": "STOCK",
      "theme": "Hardware",
      "tv_symbol": "NASDAQ:FLEX",
      "renko_status": "MIXED",
      "final_action": "WATCHLIST",
      "aligned": 0,
      "bias": "MIXED",
      "px_3m": 1,
      "px_m": -1,
      "px_w": 0,
      "streak_3m": 22,
      "streak_m": 45,
      "streak_w": 19,
      "pnl_pct": null,
      "roc14": 129.00937820159191,
      "roc21": 127.82438259506073,
      "close": 145.295,
      "reason": "No bullish Renko alignment yet"
    },
    "STOCK:TTMI": {
      "ticker": "TTMI",
      "name": "TTM Technologies",
      "asset_type": "STOCK",
      "theme": "Hardware",
      "tv_symbol": "NASDAQ:TTMI",
      "renko_status": "BULL CONFIRMED",
      "final_action": "VALIDATED",
      "aligned": 1,
      "bias": "BULL",
      "px_3m": 1,
      "px_m": 1,
      "px_w": 1,
      "streak_3m": 18,
      "streak_m": 29,
      "streak_w": 12,
      "pnl_pct": 0.0,
      "roc14": 137.33451015004414,
      "roc21": 126.39444327509999,
      "close": 215.12,
      "reason": "3M/M/W bullish + ROC14/ROC21 positive"
    },
    "STOCK:LFUS": {
      "ticker": "LFUS",
      "name": "Littelfuse",
      "asset_type": "STOCK",
      "theme": "Hardware",
      "tv_symbol": "NASDAQ:LFUS",
      "renko_status": "BULL CONFIRMED",
      "final_action": "VALIDATED",
      "aligned": 1,
      "bias": "BULL",
      "px_3m": 1,
      "px_m": 1,
      "px_w": 1,
      "streak_3m": 5,
      "streak_m": 6,
      "streak_w": 9,
      "pnl_pct": 0.0,
      "roc14": 47.274511006192895,
      "roc21": 65.44859652143963,
      "close": 480.38,
      "reason": "3M/M/W bullish + ROC14/ROC21 positive"
    }
  },
  "news": {
    "Distributors": {
      "theme": "Distributors",
      "query_url": "https://news.google.com/rss/search?q=Distributors+OR+%22technology+distributor%22+OR+%22it+distribution%22+OR+%22electronics+distribution%22+Nasdaq+OR+stocks&hl=en-US&gl=US&ceid=US:en",
      "hits": 8,
      "sources": 5,
      "keyword_hits": 1,
      "score": 72.0,
      "entries": [
        {
          "title": "Maintenance and Repair Distributors Stocks Q1 Teardown: W.W. Grainger (NYSE:GWW) Vs The Rest - Yahoo Finance",
          "source": "Yahoo Finance",
          "published": "2026-06-17T21:15:04+00:00",
          "link": "https://news.google.com/rss/articles/CBMiqgFBVV95cUxQZWJBMDhScVRfLV9zaFhyLS1HM2FMYmxpUnNDclBKcVk5M0VxTURhajhyWm1yaC1PbllLYllLVnA5MUN3Z3ZoclRhZ3NKQXpzVXc2U0t0dWUwTkpocnZ1WWt4YkpqcnNWbmU1dEZnUUw0dHFrcV9SYjR0ZWkxQ2FxSE5SVWllUEhZUkROWGpmWWVqcHQ5R2dET09zZk5lS01hWWUtcnNENW5YQQ?oc=5"
        },
        {
          "title": "IT Distribution & Solutions Stocks Q1 Highlights: ScanSource (NASDAQ:SCSC) - StockStory",
          "source": "StockStory",
          "published": "2026-06-16T10:47:50+00:00",
          "link": "https://news.google.com/rss/articles/CBMiywFBVV95cUxQZVd3UnM0T2tkbV9JeG9SaVM1Y0tWVGd0T0hzc3VGRTl2b3NsN1FWT1pMem9Eekh1ZjI5amZlWE80TVVJdnFrR3FVTVRHbXdkeDVVeXQ5aUNLQ0FBQzlDMzRXeVRZeHE1R0hGMnpseURJYUpJU0UwT3BIZ25Fb0NqVUpDTE5lc3lrTWlGeERLc1VzR0FPa1UwcUQwTlN6Mlg4ODl2dGUzNmRKaDktbThmSS13S2cybGJhMUlHa2VuZEphN1ZTVVFHYTE2OA?oc=5"
        },
        {
          "title": "Industrial Distributors Stocks Q1 Teardown: FTAI Aviation (NASDAQ:FTAI) Vs The Rest - Yahoo Finance",
          "source": "Yahoo Finance",
          "published": "2026-06-16T17:29:04+00:00",
          "link": "https://news.google.com/rss/articles/CBMiqwFBVV95cUxORnV5b3hySkg3a2RNOEQwRm9XbHgzMTh2VFFaRGdYeHJUWFFSRWJRdHp4dUIweXBKV3o1YWowUVRZRVNYSUtrVllkZHJFdFpLdHBBdzJKVWtRVDBCU3ctQTVGTGcxNzZkR0R1bTFxd3lmTGxaNk84VFZUV0hoVHFDc194V2Nrb0lHYi1wVDZZWTc0WHdHLXhtRklHXzROa1VXZFYyZmlxeDVlcnc?oc=5"
        },
        {
          "title": "Industrial Distributors Stocks Q1 Recap: Benchmarking Boise Cascade (NYSE:BCC) - The Globe and Mail",
          "source": "The Globe and Mail",
          "published": "2026-06-12T03:38:00+00:00",
          "link": "https://news.google.com/rss/articles/CBMi8gFBVV95cUxPMDJxUTR3ZjVhRkF6WlBiUG9vMERoT19ZMmFNYWR3VTNLYmtxM2kwTy1zUnBOYl8zWDFJZG1EY3Awd0tYQnhHRjI3Q3gzNkxlSC1icTc0eUFBbkM1UHhpZDZMOFlDWjk2ZEtZclRYOGJLWXJZTjVEZjFwcW51M19aUnpqcHUzTUp1ZURfTk9sc1RmbTJIUkVNWnJCbHBqaENUdTVpdzI2TWhIOUZpcVdGQnRUTlhpV1pxQlhObHFkQTlsMXVkOXAza3JSR3ctVndpTnVkNnBPVnBUQU43enFDVGprbDhfTi1kUG1jRUxwRHhvdw?oc=5"
        },
        {
          "title": "Specialty Equipment Distributors Stocks Q1 In Review: Custom Truck One Source (NYSE:CTOS) Vs Peers - TradingView",
          "source": "TradingView",
          "published": "2026-06-11T03:39:00+00:00",
          "link": "https://news.google.com/rss/articles/CBMi7AFBVV95cUxObmY2Y3U0WktETHE5Q3p4MEt0bV9JX1E0Q1k5aml2WG9ocWxIUjZKWTFOWF9sLVk3NVE4dGFrZ0xaSW9sQ3B4c1B4ck1PR2IzVVNSM1ZORmhLNEh4SzJlb2RUZWw2V1VWQmdZZnliRmtZaUdrQ0NHemJwUWIzOTEyRzJDaERBZi1FU3NlWDh3NXZ1SDhJblFMbDBLQ3ZSUHZnRkhUSlZIdGl6c2ljX1UwSHFuamh2eVU2RmdoazRYRmFhQnFRS0dWRUtWaUZHaVZEdUF6U3g3OFRCZzBJWXJKcVFUd0VfbWZCUE1OWg?oc=5"
        },
        {
          "title": "A Look Back at Industrial Distributors Stocks’ Q1 Earnings: Watsco (NYSE:WSO) Vs The Rest Of The Pack - StockStory",
          "source": "StockStory",
          "published": "2026-06-11T07:00:00+00:00",
          "link": "https://news.google.com/rss/articles/CBMixgJBVV95cUxQTmNjeVk1T2FiUFZXNjdKRlRwdllkNnRmb2dGZDZxcHhZOHo4S2p6UnhoajROcUlnazlHdlI5UU1xMzJBVFVXZ0FJc29nWFhncFFoODQ0eDRCQWlvNDk2bjNjZkZ4Y2lhVG4yN2NCaUVrZDJLVC1DQ3RKLTdud2RlamVER0JBaHpzdzBueUxaUDZIZ3ZHRnl5VlNPYTM5T19rcHFFOWdGT25GcFFZOHk2Q3ZsZmlzQlU2akJkWlROUjlUMnFrZGRiTktwaWNMWklRanNyNGRzVjg0Zm55NzN6bTlBUS1XQktPZFRMYTBJUzdNa1M4NExNNUxWeDdCYVZDbjloOW9kLXJDVHZnMGs2bm9ST3owSmROZkc2dDdYMFFmT21KeXRUTDZWaUNoaHlsM2JIMVdoSGdYaXpUbElTWU9yakxmQQ?oc=5"
        },
        {
          "title": "Specialty Equipment Distributors Stocks Q1 In Review: Custom Truck One Source (NYSE:CTOS) Vs Peers - Yahoo Finance",
          "source": "Yahoo Finance",
          "published": "2026-06-11T16:57:37+00:00",
          "link": "https://news.google.com/rss/articles/CBMiqwFBVV95cUxPVEltUjNRRjhpMjJKMDEtNmRhTXR4dFp4QW9vOXFxQzV5azdjdjJibjFOTVVVRjZNVmMtcjZFWWZhOUo4cnZxWUxzT1VKYS16S1pTbFNiWURTMW9RZll1c3czY0hpM29vdDNwZldsNkp5QUpySFFmRHZZWkw1LXNDS2xQa3FyOV8zMWhIUFhUNU5laTI0cWxpcHZ4NW5CVXdjSlRwVmJ5REdqeXc?oc=5"
        },
        {
          "title": "What Makes Pool Corporation (POOL) a Leader in Pool Distributors? - Insider Monkey",
          "source": "Insider Monkey",
          "published": "2026-06-05T15:33:06+00:00",
          "link": "https://news.google.com/rss/articles/CBMiqgFBVV95cUxNZnZsc3dRQUFIVTFJWUNSaWUyUGJkQU1hUVZsbk1EczVUck5RMlJKNUF1ZnIxY0stRWhSUm4xbmJsd1Y1R0hNRVZoM2JuaU1EU2lYaUdZNmZvNkg3bi1LTXgxM3dRTnNjWS1rVEFCQzNnUS02X2Z0OTFOcTAzUEZwb01PeE42MmNRZklsWEtTOWg0MHJSTjVHMGF1QVI4SjQ5OHVTRWNvcUhDQdIBsgFBVV95cUxPZWIyTkxtMVhDY3k2ODdEMnNHcGFPSnhHUFhSYzktTEVhdVRCNjl0VDBRVEhmZkI5VERRVnQ0VWFGWklOUHhDZm04d0ZmdTl5SVo5bjZ5T1QxNXQzaGg2S0MwcmYydC00eVY3dnpKVnQ4VmtEUkkwMDRQek9weWh2cjJ3M1d6SU1vMklQcGZ6ZVd3MEMzU085WHlFaFZTc052UERzMGNUR2JTNDdTb3lhLXZR?oc=5"
        }
      ]
    },
    "Semis": {
      "theme": "Semis",
      "query_url": "https://news.google.com/rss/search?q=Semis+OR+semiconductor+OR+chip+OR+foundry+OR+wafer+OR+%22semiconductor+equipment%22+Nasdaq+OR+stocks&hl=en-US&gl=US&ceid=US:en",
      "hits": 12,
      "sources": 12,
      "keyword_hits": 11,
      "score": 100.0,
      "entries": [
        {
          "title": "Memory shortage crisis: Apple CEO confirms higher prices are on the way; chip stocks keep soaring - Fast Company",
          "source": "Fast Company",
          "published": "2026-06-18T12:26:10+00:00",
          "link": "https://news.google.com/rss/articles/CBMiowFBVV95cUxPOUh6LTJheEpxZDlTN0l1V2o5M3hLQ2xJTjBhbkltUWxkOTB6Z1BXRVFScWNwVzlWNkV5cUpWX3M4WHZUWGo1TzVtTWJobTEyMmZET3k3RWgzUlF3MTJELVdrSHZsb3J1ZjFQcFdEOWw5b1NnTUZXXzZlM1VRc21IWEVWcXBkM1B1TXp4eUU2YWR5XzRNWDM3YkR0endWMHpZRGNN?oc=5"
        },
        {
          "title": "Vanguard VGT vs. iShares SOXX: Is Broad Tech Diversification or Semiconductor Stocks the Better Investment? - Yahoo Finance",
          "source": "Yahoo Finance",
          "published": "2026-06-18T09:20:02+00:00",
          "link": "https://news.google.com/rss/articles/CBMimAFBVV95cUxPZmFTNnZ0eXhBRUtReU5SY0ZxMEJTRlQyTjZ6WVdweGtqMURaZDB3Wm5ZSndJTnQ0b3kzQlJJcWNxS25YWHZjY2lfQWxmNzhYdEdGdU9TdlJfbUkwdGczdlo3akNMMFVFYmFtRjA5UmhyUUdwZ1J5OTRxbEpLc3NPeDFCblhCNFJCMVE2RVRIcWZENzNtU1otMA?oc=5"
        },
        {
          "title": "US chip stocks gain after Apple-Intel partnership - Investing.com",
          "source": "Investing.com",
          "published": "2026-06-18T10:07:48+00:00",
          "link": "https://news.google.com/rss/articles/CBMiqAFBVV95cUxNalZva190eUtqM0Zob2N5Ri1ZTzFqZUlYRHpvYVlsR1FxMHd4SkFSbDhSSlpKb09iaVdYNGZZWThFeU4tRlNUOUZ1QlhHcElyREQ1d0VTSUNjdll4ZWtLUDZyMlFheHhxblVBMjh0X3VpSW4yekxoc1V0cWxRQUptS1pNdmVjOXRpOHhOQWV1TFhhdng0dk1yYVFERUpGZ0h6VGZ5WXVQeWk?oc=5"
        },
        {
          "title": "US Stock Futures Rise With Intel Leading Semiconductor Rally - Bloomberg.com",
          "source": "Bloomberg.com",
          "published": "2026-06-18T11:43:07+00:00",
          "link": "https://news.google.com/rss/articles/CBMisAFBVV95cUxONS1WU3owblRvcldNU3REVFo5MldfODE1YzctWWlXX0FqM1h0VnE2ckRDM2Q4c1FTWUNNWVp5YTJjcjVDel9HN1ZvdzFSdTRYcjcwbnJweWFaRmNqcVhQdUlKOGVZUTJyRzFoU29qS1RpcVM5bFNBWm44SWdvQUpIUXpFVFZvTEZBTGNlcDRKMDJHSDlZRUVYN01hS3RTX3l2SFFLRWNtZl8tZHNjd3JYSQ?oc=5"
        },
        {
          "title": "President Trump reveals Apple-Intel domestic partnership, boosting American chip stocks - MacDailyNews",
          "source": "MacDailyNews",
          "published": "2026-06-18T11:38:55+00:00",
          "link": "https://news.google.com/rss/articles/CBMiwAFBVV95cUxQQ3k1aGRrZmhSeVRDWXh5RW9YbnJRZU5hZWtwX2I2VFM2ZE1MUlVTNjh0QnRfSENKUGVGVmNnV2t0cG9IalpIR0w0SXRFYkZUcW4tZnQ3TjAtTFlUakpQMzhXckdLNElyMVAzWmplblJibjVBQkNzUl9hLV90VHNMRnZRX3FiNHFxWXE3eXVVMDVWanB5dVFfeU1CLXVBT1NRb2FzVFZzYlJVQm9CQVA2M3RKR2gyaDRKLTMzeXJ2NmbSAcYBQVVfeXFMTV85NEkxMnlfUGNiM2hDblZRaGNlYlZaQmtvRXVWSDJFT29hTkE5MVozZG50ZnVFdVNtTjc4MWZUM25STGlNNG5vNlYwaDV6bTFrWW0tdkJXM0ZYTlN4RW92QkdINDRSdHZ3bTlJWUZQMVNJOVRaYWFKMld2NGZYcFo3MWxKdnNUU3ZYRzI5bktCUk56NHV1dmV6OXg4dWxyWTJOUTd4THFmOGRjLU1kOWxjMk9JWERJTjJzLXJYZ0w1Y08xMjZB?oc=5"
        },
        {
          "title": "Seoul stocks end at record peak of above 9,000 on extended chip rally - upi.com",
          "source": "upi.com",
          "published": "2026-06-18T09:00:18+00:00",
          "link": "https://news.google.com/rss/articles/CBMi1AFBVV95cUxNenVScEZiTnlXVkRoM2dKa2VWWmI2VVBlOG9OMy1CWjJmeHA3b3lWX2lsNUJMYlBtNmw5eWRmMTJUaURBMXRrbzF3cHdsdTNnVDZCUXJQWV9HcTc3cUQ0YmIzemhrMDRIdXFZZjlGZEFJZnM1ZkxCa3VWVGZ3eVZVNURuZXBxbV9rN2c0NWk4c2JZaEEtcXByT2dWaEtyR2JRZUpvUnZZb0xkekRRamN5V2R0OGh6LWpzN0RSZjc1Qk9hZkRVcDlCVEVnOTlwRlNnLTM4bdIB2gFBVV95cUxNaVlGR0FlX25NOTREQzFKUXlycXllSFltRU5odFhFVk1BanMtZ3c5aFJmajdlOFROYTBaclpWZkVfUlNiZkZJOXZUalNLMU9Kbk5WbGhWdDh0VHA5QjhMVFlteGp3SDB4MVhXblhUc3pTLVA0emNhNTVHZk1KZVBYX3FlbUZUaUV0RDlSZF9jWTJWRkEweTR0Tm5VUWhVSVl6ZjEyQTE4TDZaenUtbks4Ym1hNWwtSTZtM3pmYlBDTGxuenpFakdaSTcxdkJ2S2FfMHNLdFNKOWJGUQ?oc=5"
        },
        {
          "title": "Semiconductor Strength, Falling Oil Prices Lift Stocks - Schaeffer's Investment Research",
          "source": "Schaeffer's Investment Research",
          "published": "2026-06-18T15:58:39+00:00",
          "link": "https://news.google.com/rss/articles/CBMitAFBVV95cUxPcGdYQ2FMMmFIMHRtNk5RZHlFSnVFTUhZai1ONnZiLWlzWXlKbG9CcmVuR2FBQWdQeENlYzZ2NUk4R1RSVFpDWFBIbmFqWnRONUNONnFtU0ZQdXFpSVY2amdCYzRKWGFpeldKYVFyY0xPd3h3NHYtZVh6aEFyZk1LUzBjS2lmTWpVLVZ1bWZGd1ZDUDBWSUEzQll3TWhZdVRfTmM5SlNKVzhGZXNiVGV4NG0tclk?oc=5"
        },
        {
          "title": "Kevin Warsh's Bold New Strategy Is About to Spark Major Volatility for Nvidia, Micron, and AI Chip Stocks - inc.com",
          "source": "inc.com",
          "published": "2026-06-18T09:10:33+00:00",
          "link": "https://news.google.com/rss/articles/CBMiogFBVV95cUxPWWp1cVgzaGdlWTlDR2d5a3ZIbDZJVERScndxMlhFc3VhaV9PUGhoWHVVb1Jxd05FYVQwVEQtblVld3RNTTBCbVk0elNDZVJIU0hwQjR0dmdNX1U2R2Fod1NLQU1vRmdqOVlncEpqeF9TSzNmQVE2LVpINUdUZDIyNXhwMEI2T0ViOHowUklCNjUxemJmZ3pZNU9NcWVmdE9Fcnc?oc=5"
        },
        {
          "title": "Applied Materials, ASML, Lam Hit Record Highs, Lead Chip Gear Stocks Rally - Investor's Business Daily",
          "source": "Investor's Business Daily",
          "published": "2026-06-17T20:46:00+00:00",
          "link": "https://news.google.com/rss/articles/CBMikAFBVV95cUxNeTBRV3hHd0Jwb1EtREpiaXI5d2xrbUgtbWM2VldvVFg0b3hKM0lZREFRb3h0alJDLTZZRElKbS1XTkpKTy1JR0pnaHFPdGRPa2lNdVMzUmhXSkpzR0VqcWY0ZFptcHp2N1k2VXBwbWxxUklYWDVic1NpeXUwWkNjOUlsdmFLdkJtRVFvOFpxeGg?oc=5"
        },
        {
          "title": "AI Chip Stocks Are Running Out of Juice. What to Do Now. - Barron's",
          "source": "Barron's",
          "published": "2026-06-17T17:20:00+00:00",
          "link": "https://news.google.com/rss/articles/CBMic0FVX3lxTE10ZVFvc1ZnZVN5Z2RWNGVPZ3ZSUkU0bm5jTE8yTTltYjAtSjY5ck1UNmtTTjNDZ0V1WVZHX0NVanB5STlOX3JGeFRUdmlzVVlmZHZlY1FlZ3p1dDhEVm9acTczNm5NajN3STJ4YnhUZXhlbkU?oc=5"
        },
        {
          "title": "Financials Rose, Tech Fell Before Kevin Warsh Fed Debut - ETF Database",
          "source": "ETF Database",
          "published": "2026-06-18T15:19:00+00:00",
          "link": "https://news.google.com/rss/articles/CBMijAFBVV95cUxPRkVzZ0Zwb0N0LXVKR0RTOGxGbUE1QklLbFhfaUdHSS1BdzVHdzFqZkx3Y1J5SzFjV2RXZDVaREVjY0RPYlBQTE9LMVBUejV2Vkw2ODJYRTZaNHhLWjdBbzRIaktXZGFCdGdDaVBtVl9PMHpUa09zWGRHbDhvSmpsbnF1cXhRSUZCaEhwTw?oc=5"
        },
        {
          "title": "Intel shares surge after Trump details Apple chip deal (INTC:NASDAQ) - Seeking Alpha",
          "source": "Seeking Alpha",
          "published": "2026-06-18T10:18:00+00:00",
          "link": "https://news.google.com/rss/articles/CBMipgFBVV95cUxNbzA2UnZ5MG1OaGVfOHJEeFBma2ZDM0VsREhTTUFRQ0RWckhVYzJTVUgxbXMwVHJtRURqV1FyYkoycjZKNlFpRW0wSXF6LWlYWEo2cEFHbGNNaGxpVnNER2VhM0hHM0VfanVZVFcwNTI3N0RGbV9SSFJDeThsa1Zyd2VZVk1YaTdldHk1U0JpaDQ1eDZkazNyVi1XNkwzN1FfUlNmdXBB?oc=5"
        }
      ]
    },
    "IT / Internet": {
      "theme": "IT / Internet",
      "query_url": "https://news.google.com/rss/search?q=%22IT+%2F+Internet%22+OR+%22it+services%22+OR+%22internet+infrastructure%22+OR+%22it+consulting%22+OR+%22cloud+infrastructure%22+Nasdaq+OR+stocks&hl=en-US&gl=US&ceid=US:en",
      "hits": 9,
      "sources": 8,
      "keyword_hits": 8,
      "score": 100.0,
      "entries": [
        {
          "title": "IT services stocks fall after Accenture cuts guidance, Capgemini drops 8% - Investing.com",
          "source": "Investing.com",
          "published": "2026-06-18T10:57:16+00:00",
          "link": "https://news.google.com/rss/articles/CBMixwFBVV95cUxQTFJtQ1NFYi1rczJHOHQwN01WR1UyRng1Sm5aOTFUTG96OWU4RDM1MGFRckpCV3gteF81VWNpb1Fwa3pmVjBTUjFYRmF5aXpIRjc5UjgyWExlWUhPMW45dWlHckF1R2pUWU4tSkJNSDlQcUVmcHJZc0d1M25hclpLbWZkdWZ4UHgyTHFXMUMzY2tYU3B0THpzdUFEX0pRTV9jUHR4WURfU2xBZVU1RkIzdGhpSFhYRUdOckplV2g3aHU5c3FfSzBz?oc=5"
        },
        {
          "title": "U.S. Stocks Move | Accenture's guidance below expectations drags down IT services stocks; IBM (NYSE: IBM) falls over 6% - Moomoo",
          "source": "Moomoo",
          "published": "2026-06-18T14:36:18+00:00",
          "link": "https://news.google.com/rss/articles/CBMiqwFBVV95cUxQWU93VFEyYXFFOUlMWFpqNk1aNVo1WktrbUd3THJZcnUtOHp4eFBidzhSQ1huOFhUX3VtdUtmd0pOR3NFNHhUWUYwMHoyWlo3alRIbWF2UjNZenJGNTRNS2dHdFg0ZWthclprbEFfc0w2MnhoWmk4YmJHX1lLX1o5SThEdVptZFBhMWJ5LUlleUp0YVlWWHZHaGlvdFRjajFmWExaTzlHZ2lwbjA?oc=5"
        },
        {
          "title": "IBM drops after Accenture outlook, AI control worries hit IT services stocks - TechStock²",
          "source": "TechStock²",
          "published": "2026-06-18T15:04:13+00:00",
          "link": "https://news.google.com/rss/articles/CBMinAFBVV95cUxQM1RuZC0tZjZQaVAyNDRRNzJQYWNFTm9jTmRtcjV2UGVaNDRrNFluOWI4bGo4cDJ0Z1NEMjN2aGxQZnlJMFh6WENCeV8xVG53ZVJ2dWxuVFpPZlBFZEtqVEhtdVJtTXFrUUNTV01Sc1RxV0M5blpTQl9oSklxWXJ5bS0yNjl4NjRqQ21DQWVjOTRkOTZ5UUM4bXRIM1g?oc=5"
        },
        {
          "title": "Unpacking Q1 Earnings: Everforth (NYSE:EFOR) In The Context Of Other IT Services & Consulting Stocks - StockStory",
          "source": "StockStory",
          "published": "2026-06-15T07:00:00+00:00",
          "link": "https://news.google.com/rss/articles/CBMi6wFBVV95cUxQZks3Tjg1U2ktckdXWi0yYkVKcDgyUVQ0SjdURXRqZmVKNURqalNDQUkzZzVFdWVUZFZ0TDRoWl9zM3RZS3M2QlNsZDRlTFRGVDlROW8tWXAwU2dSbVBVUDJWZlpYRERCSG5vejNLbmpJSGlSSXROOEptNXkyZGRzVVQwbmdpRWhCcEJwRmFxSG9HWjhFQmRZcXczSnNERi05Wm9qeHVuMGlxRkZXQlc4X3h1dHpjSWNwdV9Hc1FJRjExM3YwVGdwYmJlb0FsOFVSQU5yUjdGcHhndHJCdVRqQ0o3VU1mWDZoLTM0?oc=5"
        },
        {
          "title": "CoreWeave joins Nasdaq-100 Index ahead of June 22 rebalancing - eciks.org",
          "source": "eciks.org",
          "published": "2026-06-16T14:44:24+00:00",
          "link": "https://news.google.com/rss/articles/CBMicEFVX3lxTE5ZNmRXcExuV3pNTVZ1bmhabkFraWpPZVNmVDhOUzRiTDVQTkJGdmxuMnh0SHVYQlNfUXg0ZUQ4cjM5aFduYm1lVFNpMGljQjRUNW1ib1lYVG5GMEFLam1yYnY2OXNlS2k3d2VVcndQRG0?oc=5"
        },
        {
          "title": "Oracle Announces Record Q4 and FY 2026 Results Driven by Cloud Infrastructure & Cloud Applications - Nasdaq",
          "source": "Nasdaq",
          "published": "2026-06-10T20:05:00+00:00",
          "link": "https://news.google.com/rss/articles/CBMiuAFBVV95cUxOa05mUU1fQ216UnB0NFJwWTdQVlhVNGd3Q1V2TmZIeXBSbXdwNS10MUI0bm5vOXppYjAwdGctZHMxNnFMbjFjV1ZGWnY4NTNIRW5UR2RlWDRycTlrVmhFRXZMV2lPOXpOMlVfN0g4NnV3QndENzUzcGxrMmNuMTNLUnJTTjNrb0Zwa2R5N2M0LWE2UzVNdDJxa1RaX3dzYzJCc3hVSzRPeHpUUEVhNXF2Ti1zVkNQWlRR?oc=5"
        },
        {
          "title": "Berenberg downgrades Cognizant as AI risks cloud IT services outlook - Investing.com",
          "source": "Investing.com",
          "published": "2026-06-17T16:47:00+00:00",
          "link": "https://news.google.com/rss/articles/CBMizgFBVV95cUxPWE1EVmtNNUw3ajN0UjNMdF8tQkVhbEVUeDZaTmIxMm1oVTdOSzRpNGIyLWhHS09RYWY0Xy1ZZ1JCdnRseHFKSExpbDFiWFh6emV0ckFUTzVvbVFkZkNDMkU2OERTTEw1TXVzWWttdDRiY1RYVTNfbTNHRUpKdDl2b0VTeTAtQWM0VEhLWVhPcVJhbzhfdmYySTlNSDF3dkVVb1JDWVUzUDNWMmM4MEdSb0dBT2s2dHhOX1RZNnJ0ZE43SExtMkp1TGIzY05zUQ?oc=5"
        },
        {
          "title": "Q1 Earnings Highs And Lows: Applied Digital (NASDAQ:APLD) Vs The Rest Of The IT Services & Other Tech Stocks - The Globe and Mail",
          "source": "The Globe and Mail",
          "published": "2026-06-08T03:35:00+00:00",
          "link": "https://news.google.com/rss/articles/CBMilgJBVV95cUxQazNROERYdmFoYXhOTXlnQUItV1V5aVBZVTRQcU1Fb1BuN3IxR1lhanBBSHRBYlJsai1CVzk2YzgyZzJfU0syRURSX3FFZXRUbnh2aTBkUGxZZURzcWhibThuM2I5R2w2aVo5UDk0UzNtNV95M1VyYzVLdFI5MUtaLVRVSUVvX0dWQ2xOS3pHeFVJSTA5ZTFQYWQxWTBFaFZJc0w2Z2FLTFQ3WkNVOW41V05DWHRrNmE4YjRReHBIcWcyRUc3STRKaVRUWFB1bW5VVlhIRTNtSk9UZlBrNnREWUdNZFhqcG9mMVJhNklDRGRSbnNHd0ZiUTNuRDBUU2FXVXA5Y19neTQxcmo4UENvLVlEY0RCQQ?oc=5"
        },
        {
          "title": "Top Japan IT Services Stocks to Watch, According to Goldman Sachs By Investing.com - Investing.com Canada",
          "source": "Investing.com Canada",
          "published": "2026-06-16T06:57:24+00:00",
          "link": "https://news.google.com/rss/articles/CBMiwwFBVV95cUxPZ3JkekxKQWk3eDlFUnlVRDBZVEd5a3ZEQ1hWd0o0Rjh4Q05XVVk0T1VVT05mMk1Ya1Z3U0YxSzRVdHRSVXVaVE1sUDFzX3M3NDl2aG8wVkZGZ1pMcHBrbFh2T203ZHo1X2IzT3B2OXVyemJyS3JUbnNJdWlzQ01kVVNWeUo2MWF3cmJwVEhkTHRIZWUwd0R0d3FNR2tjNHFpNHFwZjNBekVDcU1JVFM2MU5NRVA4ZXRucDJtM1JNaExLUHc?oc=5"
        }
      ]
    },
    "Hardware": {
      "theme": "Hardware",
      "query_url": "https://news.google.com/rss/search?q=Hardware+OR+%22electronic+components%22+OR+networking+OR+%22communications+equipment%22+OR+hardware+Nasdaq+OR+stocks&hl=en-US&gl=US&ceid=US:en",
      "hits": 12,
      "sources": 7,
      "keyword_hits": 11,
      "score": 100.0,
      "entries": [
        {
          "title": "Social Networking Stocks Q1 Highlights: Pinterest (NYSE:PINS) - Yahoo Finance",
          "source": "Yahoo Finance",
          "published": "2026-06-18T15:01:28+00:00",
          "link": "https://news.google.com/rss/articles/CBMipgFBVV95cUxPaTVBcFgzMDVsWXRxem5XUk9DOHhzX3FhaXlLWWFQVlcwSjlmd1pBMVZwMk1pTkJTdnRITFo1R0VKNjg3NWpJTVpPbkFCNC1zcGZORVZCNDNRWUNFb05uLUxOMGFWcHVSUGZRNi10RjVNSC1QbWZCa1BUaDROcklWN0pqc0tlaGViX1lPczl6dFpld0JSY0VDN3loSjE5cmdCVE1VVlR3?oc=5"
        },
        {
          "title": "Top Networking Stocks for the $1 Trillion AI Infrastructure Buildout, Per Barclays - Investing.com",
          "source": "Investing.com",
          "published": "2026-06-18T13:12:04+00:00",
          "link": "https://news.google.com/rss/articles/CBMi2gFBVV95cUxQUXBQMEFwNmkzaHJmOHdaRVdiUEZodGhIYl9kcmEwNGJHOGxqNW93bHlqS3RNSE9iS2NHTFRieGFXcFRlSHBwanh3TVV5eTd3WVhDTHBmWlpiLW1xMi1Wa1FEVng1Ulc0NGdORVY3SkpLckNFSENtSzZ5WHpudUVNbmU1R2lsLTQ2dlBUbXZxUk9XWDNvYTlGR3pvWGhUbGdJNklVRlpoa081QnBUc0FaRFBpX3hjYnpEaHJsbWh2bEg2YldiT2hjY3czQV9nZ21QSjYtUXIxSUV5UQ?oc=5"
        },
        {
          "title": "Q1 Earnings Highlights: Rogers (NYSE:ROG) Vs The Rest Of The Electronic Components & Manufacturing Stocks - StockStory",
          "source": "StockStory",
          "published": "2026-06-15T10:18:11+00:00",
          "link": "https://news.google.com/rss/articles/CBMi8AFBVV95cUxNZTRBZHlsTFBFai1rSXJXR0ZjYy16NmtEd3lCN0N3YUxoSDh3bHFKc3dlRHptbWhUblVmaE9hQ2VpQ3hjV3JMYl9TUWRlTDRzSTZjTVRtRHRoWW9HcTNMdlRjY0pQVjlxVjJiUHlwc0doV09Vak91d0JpUklMcGVwbmlGYW50QUoyd1BoMWtoTFpscmN0WUxxUnE0VzlDMC1GRmg3LWtGWS1kd3Z5eF9xakF0V0tnaE1wOHYtS1lPN3BiRDdWeUFaX0JUQ0hJYkx5WHhhLWVPLVFEaWlFQndIcnh0NkdjdlMwX1M5Y1gwUGQ?oc=5"
        },
        {
          "title": "SGX Tech Stocks Capitalise on AI Hardware Demand - Let's Data Science",
          "source": "Let's Data Science",
          "published": "2026-06-18T06:30:00+00:00",
          "link": "https://news.google.com/rss/articles/CBMilAFBVV95cUxNaVp4WnZPRVNwYUVUWDM3YUhNNjFMbzdiTE9ka2FNOE5iZmwtNlBsUXlEYXIwYURvVkd1ZlAyekF1bFhPTWQ5Y1pWTHdnRHIwdV9PbmFvUUZ6R1lrSEQ5NDJnRUQ0aG5GTVBkbWZuTThTSTdnVDJlVi1RdjdyV2V6Ry1PSnFBaHhIS1hVRWI3bVBTazZB?oc=5"
        },
        {
          "title": "10 Best Computer Hardware Stocks to Buy for the Next 5 Years - Insider Monkey",
          "source": "Insider Monkey",
          "published": "2026-06-15T13:51:52+00:00",
          "link": "https://news.google.com/rss/articles/CBMiqAFBVV95cUxQRUVHbEhLdnVSMUhMR3Bhd3ZlT0JkcTNoVkliLVBWb1o1VDdaMW8tb3EzOTZMZXRLNUM3U1JMWjF3YVpEWXc5S1hMMTczcmp5c3c5LXAtSjJRTmJ2anQ4X1pBTmdpU0lTb2pvU2N6OE5iMTZ1Uy1HaU1hd2RJZ2NWTlFheURuS3YzNW1Wd0ZXc2s5cEZTOHJvaTNfLWN2Vi11WVlGWFdMZ0I?oc=5"
        },
        {
          "title": "Quantum Computing (QUBT) is One of the Best Computer Hardware Stocks to Buy for Next 5 Years, Here is Why - Yahoo Finance",
          "source": "Yahoo Finance",
          "published": "2026-06-16T11:03:02+00:00",
          "link": "https://news.google.com/rss/articles/CBMinAFBVV95cUxQc2djWVNUejRwZTVPV0FsX215WHIycUNCZUlfdFctZncxX2RVQ0tieFU4Y05pS0FZcTIzOENJRFpNZmN4VEV4OHlqd3k0Y05jR2hBcGxITmRZWnVYVXJQcEt6WEFJNENYeHVzanZLdm1USnB3aTJKS2VlWEl2bWdlRml0OUNGMnh3U0pTTC0xUG5nSUExb0ZpWW9Ibmg?oc=5"
        },
        {
          "title": "Reflecting On Electronic Components & Manufacturing Stocks’ Q1 Earnings: CTS (NYSE:CTS) - The Globe and Mail",
          "source": "The Globe and Mail",
          "published": "2026-06-17T03:31:00+00:00",
          "link": "https://news.google.com/rss/articles/CBMi9wFBVV95cUxPdTk2bmtpYXY2Ml9EY014UTl2Yk04THBobjd6UHh1a0dVQkhSeVdXOG93VHpYZDJkUWZnOWI0bjR5aVNEbWlxWVBPdmprdy1ZaFBXVERXQ051QXloM2hLVUhyQnN0T21iUUF0RjdDM0pKUEpjRXpKZnZQNGRFODJJUU1RWU5INDRwOEROdjgxYUdycmRZajJneXF0WERfTDh1TXZjcUR3WUM3cWlHeE13ak5hRHNLLTVnLVB0a3A4WWJQUDlLa0dMZnMta2N2UTZCWGk1bDU1b2dHQTVtRHhPOElsVnJhd3cwbnlMUldqeW5CazQwNmpN?oc=5"
        },
        {
          "title": "The three major A-share indices rose amid volatility, with AI hardware stocks rallying again and PCB stocks continuing to surge; Hong Kong-listed stocks diverged, with most tech and internet stocks advancing, and MINIMAX soaring over 8%. - Moomoo",
          "source": "Moomoo",
          "published": "2026-06-17T02:12:27+00:00",
          "link": "https://news.google.com/rss/articles/CBMioAFBVV95cUxQYk8yOGxKOGUxQ3ItTnNzcU54S0F3UWotS19TX1JyM000NXczVU13dXUwd0dEMW1MOUpJREVsRmVrcWJrbTFvaF9Fb3dDWkdQMGtKSENHM2hWMEdZRnc5dmdWVXhTejRCVGpFck4wZURlM2NBZlRreU04anBIcnRIWWFxbTZ4RWhlcFRSNW1PaGNJV1o0Rzgxc3hJUDNUQ1JS?oc=5"
        },
        {
          "title": "Q1 Earnings Highs And Lows: Littelfuse (NASDAQ:LFUS) Vs The Rest Of The Electronic Components Stocks - StockStory",
          "source": "StockStory",
          "published": "2026-06-14T07:00:00+00:00",
          "link": "https://news.google.com/rss/articles/CBMi6wFBVV95cUxOVEVWUFE2SGZBM3VxWVl0R1p5M1dnUHliTEhLYU92bUZTTGN6STY0bnRZVUMyUjJPNEJCT3d5eWcwcjBEX3lMWUdlak03RWE5OVhhcnNuX2Zjc0N3RU1USjcwemxGcV8tLUItWURNVmx0ODJPeXU5SjBjRHhfalNvSmJ1UkpUTk5RVWIzRDIweTlhTG9DUXdBM1ZLeHZ0Z3F6VDhGUGc0SjdRM3VzVFBaSDFEaHlsWlVyQ3g5RzBEdDRjRVVaSzkzTWV0Q3gxUGVWSG1MTUZiN1RjZHc2TjlxNjBBR2pPUE9weHVF?oc=5"
        },
        {
          "title": "10 Best Computer Hardware Stocks to Buy for the Next 5 Years - Insider Monkey",
          "source": "Insider Monkey",
          "published": "2026-06-15T14:56:45+00:00",
          "link": "https://news.google.com/rss/articles/CBMiuAFBVV95cUxONFktcTZ0Mzhmd0xUcXFXRE9OMl9HOU5hbHN5OXIzcFNVX2Jfb3Q0OC1TTFkwR2JqT2tTSUVpX1dQN3p1Nm1kSG50eDJXRi14anpMb1NULXltUzNSRXZsSGxYM1piVldqcGVBbGtsQU1IWk1wbU8yYktvcWZPTTh5amN3bVpwR21zSWFObWhvN3RlcUFkbFVqWjhGUjhwWFc5VlBTVHozc2VuUEZJRE9NZ2hUNDJxSWRE?oc=5"
        },
        {
          "title": "A Look Back at Social Networking Stocks’ Q1 Earnings: Yelp (NYSE:YELP) Vs The Rest Of The Pack - Yahoo Finance",
          "source": "Yahoo Finance",
          "published": "2026-06-15T17:00:07+00:00",
          "link": "https://news.google.com/rss/articles/CBMioAFBVV95cUxQeGJ0VDduenZ6UExqZHlHYW0wbkcweFFMZU9IRnVUeVVIUk9TTHdMMEJvTUdSWG9pMnBfMEVzOVEyZm5vaXItaUdWM3hWcFpkN1RKSlBSZkx4ZVlwX3lTaklhLXVCSE9mY0hnXzlqRWxvRkNJdHZIMW1KekNWUk5SRE1QM3Jadmp0bUVWVU9iVkxxV252QVktQzZxRVdnZTVp?oc=5"
        },
        {
          "title": "IT Distribution & Solutions Stocks Q1 Highlights: ScanSource (NASDAQ:SCSC) - StockStory",
          "source": "StockStory",
          "published": "2026-06-16T10:47:50+00:00",
          "link": "https://news.google.com/rss/articles/CBMiywFBVV95cUxQZVd3UnM0T2tkbV9JeG9SaVM1Y0tWVGd0T0hzc3VGRTl2b3NsN1FWT1pMem9Eekh1ZjI5amZlWE80TVVJdnFrR3FVTVRHbXdkeDVVeXQ5aUNLQ0FBQzlDMzRXeVRZeHE1R0hGMnpseURJYUpJU0UwT3BIZ25Fb0NqVUpDTE5lc3lrTWlGeERLc1VzR0FPa1UwcUQwTlN6Mlg4ODl2dGUzNmRKaDktbThmSS13S2cybGJhMUlHa2VuZEphN1ZTVVFHYTE2OA?oc=5"
        }
      ]
    },
    "Logiciels": {
      "theme": "Logiciels",
      "query_url": "https://news.google.com/rss/search?q=Logiciels+OR+software+OR+saas+OR+%22application+software%22+OR+%22cloud+software%22+Nasdaq+OR+stocks&hl=en-US&gl=US&ceid=US:en",
      "hits": 12,
      "sources": 8,
      "keyword_hits": 8,
      "score": 100.0,
      "entries": [
        {
          "title": "3 Software Stocks That Fall Short - Yahoo Finance",
          "source": "Yahoo Finance",
          "published": "2026-06-18T11:49:28+00:00",
          "link": "https://news.google.com/rss/articles/CBMimAFBVV95cUxObmpFcGZzVEVKR1NFVU1FTFVsc2JUSE1NUlBfVXhkVEFUd0dJQXFpWDVqakZHZzl6RTF2RDQyTGlQNFhiM05jX1h0Y3lLck1wNElxbExURmZsMjFDNjljY1E2ek9NSWV0NFlLcWtueWZBMnZGdzU5MkZSMzdPT3FWUksySU9xYkV5SVZQTnNDLTVyU0NNWlYyOQ?oc=5"
        },
        {
          "title": "3 Software Stocks That Fall Short - StockStory",
          "source": "StockStory",
          "published": "2026-06-18T09:45:57+00:00",
          "link": "https://news.google.com/rss/articles/CBMimwFBVV95cUxQYjJQQnhxS1VwM01LbWR1SUF2cTNaUFRmOFZ6WXlhRWpqWHlnRDlTNFZzTnBRMUxubTJ5SmphSEpNWXV0QS1vQTVnUzNWV0pkQ2dGRDF4c0x0MTNkalNUU3RoTmN2ZGNDZjFwMklJVnZrSmdWSlpnVTBvWEkwckpYc2tLWGl4NmFUcmFjYXBwOWJIbW9oVDRtRHNoOA?oc=5"
        },
        {
          "title": "Software Stocks Are Going Down, No Matter What Happens With AI (BATS:IGV) - Seeking Alpha",
          "source": "Seeking Alpha",
          "published": "2026-06-15T18:56:55+00:00",
          "link": "https://news.google.com/rss/articles/CBMipAFBVV95cUxNWlhEd1I4SzFpdUJ5b2Z0Qk8xb2h1QTBMOVVRYWYyRmM5SGpuYnltdS1wV3JfWE8zdHhKSEFIXzBLZTgyTkN6Nk40QXZBTFdtaWUweGxmWktScjhRRlVWYmlhUXZicmZPRFkyTDk0NlpHRnBIREFWWWx3dTBRaDRTY1R6RU5LeGRraEFiY185TFg4TU5lVTJRT0Ytc2pKTm1sUDk4TA?oc=5"
        },
        {
          "title": "Is Intuit (INTU) One of the Best Generative AI Software Stocks to Buy? - Insider Monkey",
          "source": "Insider Monkey",
          "published": "2026-06-18T15:18:43+00:00",
          "link": "https://news.google.com/rss/articles/CBMisAFBVV95cUxOdGlydFdxU1hnWW9iTmdQVGdEbXJkb0ZiUW91dllENGVVZWdxN0QxQWNvRWJ4OUF6UU1ldmQ2OXZfczBmNnFQTldneWpicFphQVJjcXVhLVVpTVkwR21lV1BmdnJBOTRZSVFrUGV5R1E2QjBScHRyRWoybmRFaWNGbjRlRTRZek1zY21pVVNJc0M2ay1hM2JlamhlSURYOGJsWVZZd0hWYUpIT210a1Qwc9IBuAFBVV95cUxQdU8yTkx1Q2dnLWxHaEhyd2NLZlFWU3ZPUEtSWUdxR01YVnRPMmNfcnJHaTRQc3ZFM2JHa2RiX3VhSkttbGVFTUctdE54WDRJLUxwUFo3ZnZBeldzNXhjNUpGUTk1WHROMkM5RmNIcHBHUjFOX1psMlFscXZSOHVXVnYxQlFZRk9vbUZ6Tll4YWNCUjg2NngySGtoV21wV1FKRHl6eWh5YU4wTUtrYy1wQXJQQmROY1J4?oc=5"
        },
        {
          "title": "Broader Market Weakens as Energy and Software Stocks Fall - Barchart.com",
          "source": "Barchart.com",
          "published": "2026-06-16T15:15:38+00:00",
          "link": "https://news.google.com/rss/articles/CBMiowFBVV95cUxQQXN3VGMwYnJVV3BBMVIwSGprS3NnVndlZ0prUVo2LU45SjdVbFdaWVhEVEV6MkNMd1Y5V3dXNlNBTXltZEp5dVI4NEgwWWhxbTNqYjB5VDBKRmNBLTNPNlpuS0pubHJUa0pTdkFkRzZzQ2xycnNHS2FFOVlDemNsTk1NRUl2eG9EenlaRjEzalloX3Q4dXZseVR0ejZDVnNqYTBB?oc=5"
        },
        {
          "title": "European Software Stocks Fall After Accenture Cuts Guidance - marketscreener.com",
          "source": "marketscreener.com",
          "published": "2026-06-18T12:45:16+00:00",
          "link": "https://news.google.com/rss/articles/CBMisgFBVV95cUxQMG9xWTZ6UXp3MWxleGxKVHF5OTdCNkxMU3ZSV1JWWGZMT3l5MlhqZDdCdTRfcGVxSm0tTVQ4S0NITnMxMWpIVk5USk9qV2d5WE5XSWRRV3cxMUZXeGFzR1FvekdEWFNVYWhxeGlsS1hxbndEdE9rVXkxUFZvR1ZqOVlXd0tlLV9kRWFMallDempRMzA1dGJTdzhYcjk3WFdsNjNRY3hTU0lqd3RVTENkbmZB?oc=5"
        },
        {
          "title": "Spotlight On Harrow And 2 Other Growth Stocks With Strong Insider Backing - simplywall.st",
          "source": "simplywall.st",
          "published": "2026-06-18T11:11:33+00:00",
          "link": "https://news.google.com/rss/articles/CBMixgFBVV95cUxNVWNYTTVVUjVhQW9KU0ZfenAzSDNpVWxQZkpWWDZfSkhTaGV1N3ZwNWFwYUJlLXJPME4wWF9USHM2WXczYXlFRGptU2JJN1NSRHFOclV4MnBBQ3VGNzRWQy1ueVZvUDVwSWFzS0h2N3JocDFOZTZlSG5MM0FvemF0LURscXJsaGNZWEZvdENNemF6ZlZnSTRvc2pLenVLZDE3YnNuRENmWXpScnJvVC1ydEg1OTVHTk9LcEpjVmRQNW9yVGVIM1HSAcsBQVVfeXFMTjFseHoyY0h4UFc2Nk1CQkVzRW1zOFdjWEdTU09rVmQ3T2pndDgwcDlHRG5pLWk1WDJpcGh5a0hGRXpERkducmRmclpYTWpMcUpkX1FlcUVtc2lSWEtPcGwxazBzeU90Z0t4a3JVZDlSYjM2b2d2QW5XYVFScV9mTWdVb3daUWdUcVhEM3psYUpsZHlJSkpndmZUcnJQc2g3VXBJRzR2VGNYTzFsT1hWMTRwNUxENEtRWFpvM1NnMzM0bE1NbjhlREZsMFk?oc=5"
        },
        {
          "title": "Spotting Winners: Autodesk (NASDAQ:ADSK) And Design Software Stocks In Q1 - Yahoo Finance",
          "source": "Yahoo Finance",
          "published": "2026-06-18T14:53:28+00:00",
          "link": "https://news.google.com/rss/articles/CBMipAFBVV95cUxQckEzaEtMWDNyYV9fUnc4bmxLdzk0RzQzVUtJd1ptdU5JRnNVM0Jvb1dzRmpjU3BLa19weGpSQ3Z3N0U2SnJLMEFUVzR6U3VaNVp1VkNwOHk5ZWlzSlpGVGlXU0NZSENYNDJTNXpGTWdfSDNIRV93ZEVudU5NMnVpT2VGYloxMU1KR3A1RTRlMS1Ld0pPamluSko1MHRUNVVNLXVnLQ?oc=5"
        },
        {
          "title": "RingCentral and CLEAR Secure Stocks Trade Down, What You Need To Know - StockStory",
          "source": "StockStory",
          "published": "2026-06-18T06:14:52+00:00",
          "link": "https://news.google.com/rss/articles/CBMixgFBVV95cUxPTFQ3azk4NnZ2N0dfQTUtbXdQYnA3R05lcTdfUWlGeWNRUzhuYmlxdGRHc0tzRE9kVTE4UkJkSjF3OWhZdC1DQ3NvSTB0bVNuTjd0bWdobDB3TkxQZFQwdDhJd1NKTUxraWVhMjlJOHBzdEExMkdEOWgtTWZmcDBYWmlSZzNJWkxUeTJvcnhUSmY5TFgyT2cxVWdhdjFxZ09wRlJaYlYxLTFUOUx3SGpmS3RjZWUwZzRjSnZaa3B0OFNrQjJIOFE?oc=5"
        },
        {
          "title": "SaaSpocalypse 2.0: 3 SaaS Stocks to Buy on the Latest Sell-Off - Yahoo Finance",
          "source": "Yahoo Finance",
          "published": "2026-06-12T15:50:00+00:00",
          "link": "https://news.google.com/rss/articles/CBMikwFBVV95cUxOMWJEZEFVZlVqRHdEVWY4S1BUbGhLNXJ6bWRoQm1EOUJyWmpjZTJIZ3dwWElORTk5QkcwV1ptb0tpQ3FCSXdTSEpzRWt5THJ2UVlsVHNRNW9CbkxGY2d2aW8zRkRHa2Ewd1BTRlV3LWNWN0F0SHdZeGk0eDNjeFpKUWRKYUZFUHJkVDNlQ0tHallkTVU?oc=5"
        },
        {
          "title": "Appian, ZoomInfo, and Salesforce Shares Plummet, What You Need To Know - StockStory",
          "source": "StockStory",
          "published": "2026-06-18T06:41:41+00:00",
          "link": "https://news.google.com/rss/articles/CBMiyAFBVV95cUxNZ1R4MW5nbE1aOUtQS2NuVFZDQlFxbTU0M29qYnM3NEVDVC10amNpYktFWWQtTTZEVU5wZ3hCNXBhWEZxaEVJRHV6SGVvVE5vYUotdmNfU1E1LW4yYnZubmUybGtoclNNZkluR19vZ0FzZ0IwV21lc0xMVXhXY2xsTG9RRHoyTnI1N3NLVEZiSmR1dlJuVnBVOFRxY2hKRmxjZ1ViTVBmYzZCa2lHRWN6ck5hd0ppLTBNenRoUHp2VExqVGs0bnhPbw?oc=5"
        },
        {
          "title": "Best Income Stocks to Buy for June 18th - Yahoo! Finance Canada",
          "source": "Yahoo! Finance Canada",
          "published": "2026-06-18T08:23:00+00:00",
          "link": "https://news.google.com/rss/articles/CBMiggFBVV95cUxQLUY5elAyWGIyT050Y0FWckJkTzZtczNmRjJqb0JFTTcwTElWZmdMMkVOMF8zQ0t6em5ETzZBUTZyRXN5c1VteVcyakcwTFRjUEdiX0c1U0x3bUgxQ2o3VW5JVURTUWJ0OENQazExMW9UVFh4Q2RVVlJwLUwxd3J2MHVR?oc=5"
        }
      ]
    }
  }
}