{
  "updated_at": "2026-04-03T22:55:17",
  "active_pairs": [
    {
      "pair": "AUDNZD",
      "direction": "BULL",
      "signal": "BULL",
      "score": 1.1913,
      "sar15_confirmed": true
    },
    {
      "pair": "NZDUSD",
      "direction": "BEAR",
      "signal": "BEAR",
      "score": -0.7661,
      "sar15_confirmed": true
    },
    {
      "pair": "GBPUSD",
      "direction": "BEAR",
      "signal": "BEAR",
      "score": -0.4415,
      "sar15_confirmed": true
    },
    {
      "pair": "EURNZD",
      "direction": "BULL",
      "signal": "LONG",
      "score": 0.8244,
      "sar15_confirmed": true
    },
    {
      "pair": "NZDJPY",
      "direction": "BEAR",
      "signal": "BEAR",
      "score": -0.7146,
      "sar15_confirmed": true
    },
    {
      "pair": "NZDCHF",
      "direction": "BEAR",
      "signal": "BEAR",
      "score": -0.5255,
      "sar15_confirmed": true
    },
    {
      "pair": "AUDUSD",
      "direction": "BEAR",
      "signal": "BEAR",
      "score": -0.4457,
      "sar15_confirmed": true
    },
    {
      "pair": "GBPNZD",
      "direction": "BULL",
      "signal": "BULL",
      "score": 0.3786,
      "sar15_confirmed": true
    }
  ]
}